{"pagelen": 50, "values": [{"update": {"description": "Support loading from an SDF string.", "title": "Load from string", "destination": {"commit": {"hash": "866bf97cc072", "type": "commit", "links": {"self": {"href": "data/repositories/osrf/sdformat/commit/866bf97cc072.json"}, "html": {"href": "#!/osrf/sdformat/commits/866bf97cc072"}}}, "repository": {"links": {"self": {"href": "data/repositories/osrf/sdformat.json"}, "html": {"href": "#!/osrf/sdformat"}, "avatar": {"href": "data/bytebucket.org/ravatar/{b6d52f9f-b070-41c0-807c-94af07ea375b}ts=1606789"}}, "type": "repository", "name": "sdformat", "full_name": "osrf/sdformat", "uuid": "{b6d52f9f-b070-41c0-807c-94af07ea375b}"}, "branch": {"name": "default"}}, "reason": "", "source": {"commit": {"hash": "4d92e98c331d", "type": "commit", "links": {"self": {"href": "data/repositories/osrf/sdformat/commit/4d92e98c331d.json"}, "html": {"href": "#!/osrf/sdformat/commits/4d92e98c331d"}}}, "repository": {"links": {"self": {"href": "data/repositories/osrf/sdformat.json"}, "html": {"href": "#!/osrf/sdformat"}, "avatar": {"href": "data/bytebucket.org/ravatar/{b6d52f9f-b070-41c0-807c-94af07ea375b}ts=1606789"}}, "type": "repository", "name": "sdformat", "full_name": "osrf/sdformat", "uuid": "{b6d52f9f-b070-41c0-807c-94af07ea375b}"}, "branch": {"name": "dom_load_string"}}, "state": "MERGED", "author": {"display_name": "Nate Koenig", "uuid": "{c862cdd9-fcc8-4419-9fc7-e20db14b8fcb}", "links": {"self": {"href": "https://api.bitbucket.org/2.0/users/%7Bc862cdd9-fcc8-4419-9fc7-e20db14b8fcb%7D"}, "html": {"href": "https://bitbucket.org/%7Bc862cdd9-fcc8-4419-9fc7-e20db14b8fcb%7D/"}, "avatar": {"href": "https://avatar-management--avatars.us-west-2.prod.public.atl-paas.net/557058:095b1e12-74ed-4e20-b44f-2f0745b616e0/ca24bb11-4787-4b14-a20d-d91835e9bde2/128"}}, "nickname": "Nathan Koenig", "type": "user", "account_id": "557058:095b1e12-74ed-4e20-b44f-2f0745b616e0"}, "date": "2018-03-26T19:37:54.467086+00:00"}, "pull_request": {"type": "pullrequest", "id": 420, "links": {"self": {"href": "data/repositories/osrf/sdformat/pullrequests/420.json"}, "html": {"href": "#!/osrf/sdformat/pull-requests/420"}}, "title": "Load from string"}}, {"update": {"description": "Support loading from an SDF string.", "title": "Load from string", "destination": {"commit": {"hash": "866bf97cc072", "type": "commit", "links": {"self": {"href": "data/repositories/osrf/sdformat/commit/866bf97cc072.json"}, "html": {"href": "#!/osrf/sdformat/commits/866bf97cc072"}}}, "repository": {"links": {"self": {"href": "data/repositories/osrf/sdformat.json"}, "html": {"href": "#!/osrf/sdformat"}, "avatar": {"href": "data/bytebucket.org/ravatar/{b6d52f9f-b070-41c0-807c-94af07ea375b}ts=1606789"}}, "type": "repository", "name": "sdformat", "full_name": "osrf/sdformat", "uuid": "{b6d52f9f-b070-41c0-807c-94af07ea375b}"}, "branch": {"name": "default"}}, "reason": "", "source": {"commit": {"hash": "4d92e98c331d", "type": "commit", "links": {"self": {"href": "data/repositories/osrf/sdformat/commit/4d92e98c331d.json"}, "html": {"href": "#!/osrf/sdformat/commits/4d92e98c331d"}}}, "repository": {"links": {"self": {"href": "data/repositories/osrf/sdformat.json"}, "html": {"href": "#!/osrf/sdformat"}, "avatar": {"href": "data/bytebucket.org/ravatar/{b6d52f9f-b070-41c0-807c-94af07ea375b}ts=1606789"}}, "type": "repository", "name": "sdformat", "full_name": "osrf/sdformat", "uuid": "{b6d52f9f-b070-41c0-807c-94af07ea375b}"}, "branch": {"name": "dom_load_string"}}, "state": "OPEN", "author": {"display_name": "Nate Koenig", "uuid": "{c862cdd9-fcc8-4419-9fc7-e20db14b8fcb}", "links": {"self": {"href": "https://api.bitbucket.org/2.0/users/%7Bc862cdd9-fcc8-4419-9fc7-e20db14b8fcb%7D"}, "html": {"href": "https://bitbucket.org/%7Bc862cdd9-fcc8-4419-9fc7-e20db14b8fcb%7D/"}, "avatar": {"href": "https://avatar-management--avatars.us-west-2.prod.public.atl-paas.net/557058:095b1e12-74ed-4e20-b44f-2f0745b616e0/ca24bb11-4787-4b14-a20d-d91835e9bde2/128"}}, "nickname": "Nathan Koenig", "type": "user", "account_id": "557058:095b1e12-74ed-4e20-b44f-2f0745b616e0"}, "date": "2018-03-26T19:37:34.440658+00:00"}, "pull_request": {"type": "pullrequest", "id": 420, "links": {"self": {"href": "data/repositories/osrf/sdformat/pullrequests/420.json"}, "html": {"href": "#!/osrf/sdformat/pull-requests/420"}}, "title": "Load from string"}}, {"approval": {"date": "2018-03-24T18:03:02.018425+00:00", "pullrequest": {"type": "pullrequest", "id": 420, "links": {"self": {"href": "data/repositories/osrf/sdformat/pullrequests/420.json"}, "html": {"href": "#!/osrf/sdformat/pull-requests/420"}}, "title": "Load from string"}, "user": {"display_name": "Carlos Ag\u00fcero", "uuid": "{da8a8e89-4bb0-421b-bd0e-dbbed3d4ed6a}", "links": {"self": {"href": "https://api.bitbucket.org/2.0/users/%7Bda8a8e89-4bb0-421b-bd0e-dbbed3d4ed6a%7D"}, "html": {"href": "https://bitbucket.org/%7Bda8a8e89-4bb0-421b-bd0e-dbbed3d4ed6a%7D/"}, "avatar": {"href": "data/secure.gravatar.com/avatar/692bf15758111acaddae4da15a47f9e5d=httpsavatar-management--avatars.us-west-2.prod.public.atl-paas.netinitialsCA-0.png"}}, "nickname": "caguero", "type": "user", "account_id": "557058:4ded1ddf-947e-4154-bbd1-3dba24f1bdbd"}}, "pull_request": {"type": "pullrequest", "id": 420, "links": {"self": {"href": "data/repositories/osrf/sdformat/pullrequests/420.json"}, "html": {"href": "#!/osrf/sdformat/pull-requests/420"}}, "title": "Load from string"}}, {"comment": {"links": {"self": {"href": "data/repositories/osrf/sdformat/pullrequests/420/comments/59783098.json"}, "html": {"href": "#!/osrf/sdformat/pull-requests/420/_/diff#comment-59783098"}}, "deleted": false, "pullrequest": {"type": "pullrequest", "id": 420, "links": {"self": {"href": "data/repositories/osrf/sdformat/pullrequests/420.json"}, "html": {"href": "#!/osrf/sdformat/pull-requests/420"}}, "title": "Load from string"}, "content": {"raw": "Looks good to me.", "markup": "markdown", "html": "<p>Looks good to me.</p>", "type": "rendered"}, "created_on": "2018-03-24T18:02:57.832538+00:00", "user": {"display_name": "Carlos Ag\u00fcero", "uuid": "{da8a8e89-4bb0-421b-bd0e-dbbed3d4ed6a}", "links": {"self": {"href": "https://api.bitbucket.org/2.0/users/%7Bda8a8e89-4bb0-421b-bd0e-dbbed3d4ed6a%7D"}, "html": {"href": "https://bitbucket.org/%7Bda8a8e89-4bb0-421b-bd0e-dbbed3d4ed6a%7D/"}, "avatar": {"href": "data/secure.gravatar.com/avatar/692bf15758111acaddae4da15a47f9e5d=httpsavatar-management--avatars.us-west-2.prod.public.atl-paas.netinitialsCA-0.png"}}, "nickname": "caguero", "type": "user", "account_id": "557058:4ded1ddf-947e-4154-bbd1-3dba24f1bdbd"}, "updated_on": "2018-03-24T18:02:57.835883+00:00", "type": "pullrequest_comment", "id": 59783098}, "pull_request": {"type": "pullrequest", "id": 420, "links": {"self": {"href": "data/repositories/osrf/sdformat/pullrequests/420.json"}, "html": {"href": "#!/osrf/sdformat/pull-requests/420"}}, "title": "Load from string"}}, {"comment": {"links": {"self": {"href": "data/repositories/osrf/sdformat/pullrequests/420/comments/59783046.json"}, "html": {"href": "#!/osrf/sdformat/pull-requests/420/_/diff#comment-59783046"}}, "deleted": false, "pullrequest": {"type": "pullrequest", "id": 420, "links": {"self": {"href": "data/repositories/osrf/sdformat/pullrequests/420.json"}, "html": {"href": "#!/osrf/sdformat/pull-requests/420"}}, "title": "Load from string"}, "content": {"raw": "`_SDF_VISIBLE_HH_`?", "markup": "markdown", "html": "<p><code>_SDF_VISIBLE_HH_</code>?</p>", "type": "rendered"}, "created_on": "2018-03-24T17:58:50.442590+00:00", "user": {"display_name": "Carlos Ag\u00fcero", "uuid": "{da8a8e89-4bb0-421b-bd0e-dbbed3d4ed6a}", "links": {"self": {"href": "https://api.bitbucket.org/2.0/users/%7Bda8a8e89-4bb0-421b-bd0e-dbbed3d4ed6a%7D"}, "html": {"href": "https://bitbucket.org/%7Bda8a8e89-4bb0-421b-bd0e-dbbed3d4ed6a%7D/"}, "avatar": {"href": "data/secure.gravatar.com/avatar/692bf15758111acaddae4da15a47f9e5d=httpsavatar-management--avatars.us-west-2.prod.public.atl-paas.netinitialsCA-0.png"}}, "nickname": "caguero", "type": "user", "account_id": "557058:4ded1ddf-947e-4154-bbd1-3dba24f1bdbd"}, "inline": {}, "updated_on": "2018-03-24T17:58:56.108407+00:00", "type": "pullrequest_comment", "id": 59783046}, "pull_request": {"type": "pullrequest", "id": 420, "links": {"self": {"href": "data/repositories/osrf/sdformat/pullrequests/420.json"}, "html": {"href": "#!/osrf/sdformat/pull-requests/420"}}, "title": "Load from string"}}, {"update": {"description": "Support loading from an SDF string.", "title": "Load from string", "destination": {"commit": {"hash": "866bf97cc072", "type": "commit", "links": {"self": {"href": "data/repositories/osrf/sdformat/commit/866bf97cc072.json"}, "html": {"href": "#!/osrf/sdformat/commits/866bf97cc072"}}}, "repository": {"links": {"self": {"href": "data/repositories/osrf/sdformat.json"}, "html": {"href": "#!/osrf/sdformat"}, "avatar": {"href": "data/bytebucket.org/ravatar/{b6d52f9f-b070-41c0-807c-94af07ea375b}ts=1606789"}}, "type": "repository", "name": "sdformat", "full_name": "osrf/sdformat", "uuid": "{b6d52f9f-b070-41c0-807c-94af07ea375b}"}, "branch": {"name": "default"}}, "reason": "", "source": {"commit": {"hash": "609fefa24699", "type": "commit", "links": {"self": {"href": "data/repositories/osrf/sdformat/commit/609fefa24699.json"}, "html": {"href": "#!/osrf/sdformat/commits/609fefa24699"}}}, "repository": {"links": {"self": {"href": "data/repositories/osrf/sdformat.json"}, "html": {"href": "#!/osrf/sdformat"}, "avatar": {"href": "data/bytebucket.org/ravatar/{b6d52f9f-b070-41c0-807c-94af07ea375b}ts=1606789"}}, "type": "repository", "name": "sdformat", "full_name": "osrf/sdformat", "uuid": "{b6d52f9f-b070-41c0-807c-94af07ea375b}"}, "branch": {"name": "dom_load_string"}}, "state": "OPEN", "author": {"display_name": "Steve Peters", "uuid": "{2ccfed09-18b8-4921-8d58-15ef01092802}", "links": {"self": {"href": "https://api.bitbucket.org/2.0/users/%7B2ccfed09-18b8-4921-8d58-15ef01092802%7D"}, "html": {"href": "https://bitbucket.org/%7B2ccfed09-18b8-4921-8d58-15ef01092802%7D/"}, "avatar": {"href": "data/secure.gravatar.com/avatar/1fb4816dad9e68337d3096f750951f6cd=httpsavatar-management--avatars.us-west-2.prod.public.atl-paas.netinitialsSP-1.png"}}, "nickname": "Steven Peters", "type": "user", "account_id": "557058:5de38267-b118-494c-aa76-4fab35448816"}, "date": "2018-03-22T18:12:35.768476+00:00"}, "pull_request": {"type": "pullrequest", "id": 420, "links": {"self": {"href": "data/repositories/osrf/sdformat/pullrequests/420.json"}, "html": {"href": "#!/osrf/sdformat/pull-requests/420"}}, "title": "Load from string"}}, {"update": {"description": "Support loading from an SDF string.", "title": "Load from string", "destination": {"commit": {"hash": "652ce6cc1463", "type": "commit", "links": {"self": {"href": "data/repositories/osrf/sdformat/commit/652ce6cc1463.json"}, "html": {"href": "#!/osrf/sdformat/commits/652ce6cc1463"}}}, "repository": {"links": {"self": {"href": "data/repositories/osrf/sdformat.json"}, "html": {"href": "#!/osrf/sdformat"}, "avatar": {"href": "data/bytebucket.org/ravatar/{b6d52f9f-b070-41c0-807c-94af07ea375b}ts=1606789"}}, "type": "repository", "name": "sdformat", "full_name": "osrf/sdformat", "uuid": "{b6d52f9f-b070-41c0-807c-94af07ea375b}"}, "branch": {"name": "default"}}, "reason": "", "source": {"commit": {"hash": "2198118c2333", "type": "commit", "links": {"self": {"href": "data/repositories/osrf/sdformat/commit/2198118c2333.json"}, "html": {"href": "#!/osrf/sdformat/commits/2198118c2333"}}}, "repository": {"links": {"self": {"href": "data/repositories/osrf/sdformat.json"}, "html": {"href": "#!/osrf/sdformat"}, "avatar": {"href": "data/bytebucket.org/ravatar/{b6d52f9f-b070-41c0-807c-94af07ea375b}ts=1606789"}}, "type": "repository", "name": "sdformat", "full_name": "osrf/sdformat", "uuid": "{b6d52f9f-b070-41c0-807c-94af07ea375b}"}, "branch": {"name": "dom_load_string"}}, "state": "OPEN", "author": {"display_name": "Nate Koenig", "uuid": "{c862cdd9-fcc8-4419-9fc7-e20db14b8fcb}", "links": {"self": {"href": "https://api.bitbucket.org/2.0/users/%7Bc862cdd9-fcc8-4419-9fc7-e20db14b8fcb%7D"}, "html": {"href": "https://bitbucket.org/%7Bc862cdd9-fcc8-4419-9fc7-e20db14b8fcb%7D/"}, "avatar": {"href": "https://avatar-management--avatars.us-west-2.prod.public.atl-paas.net/557058:095b1e12-74ed-4e20-b44f-2f0745b616e0/ca24bb11-4787-4b14-a20d-d91835e9bde2/128"}}, "nickname": "Nathan Koenig", "type": "user", "account_id": "557058:095b1e12-74ed-4e20-b44f-2f0745b616e0"}, "date": "2018-03-22T15:44:28.699011+00:00"}, "pull_request": {"type": "pullrequest", "id": 420, "links": {"self": {"href": "data/repositories/osrf/sdformat/pullrequests/420.json"}, "html": {"href": "#!/osrf/sdformat/pull-requests/420"}}, "title": "Load from string"}}, {"update": {"description": "Support loading from an SDF string.", "title": "Load from string", "destination": {"commit": {"hash": "652ce6cc1463", "type": "commit", "links": {"self": {"href": "data/repositories/osrf/sdformat/commit/652ce6cc1463.json"}, "html": {"href": "#!/osrf/sdformat/commits/652ce6cc1463"}}}, "repository": {"links": {"self": {"href": "data/repositories/osrf/sdformat.json"}, "html": {"href": "#!/osrf/sdformat"}, "avatar": {"href": "data/bytebucket.org/ravatar/{b6d52f9f-b070-41c0-807c-94af07ea375b}ts=1606789"}}, "type": "repository", "name": "sdformat", "full_name": "osrf/sdformat", "uuid": "{b6d52f9f-b070-41c0-807c-94af07ea375b}"}, "branch": {"name": "default"}}, "reason": "", "source": {"commit": {"hash": "2d030756b9a3", "type": "commit", "links": {"self": {"href": "data/repositories/osrf/sdformat/commit/2d030756b9a3.json"}, "html": {"href": "#!/osrf/sdformat/commits/2d030756b9a3"}}}, "repository": {"links": {"self": {"href": "data/repositories/osrf/sdformat.json"}, "html": {"href": "#!/osrf/sdformat"}, "avatar": {"href": "data/bytebucket.org/ravatar/{b6d52f9f-b070-41c0-807c-94af07ea375b}ts=1606789"}}, "type": "repository", "name": "sdformat", "full_name": "osrf/sdformat", "uuid": "{b6d52f9f-b070-41c0-807c-94af07ea375b}"}, "branch": {"name": "dom_load_string"}}, "state": "OPEN", "author": {"display_name": "Nate Koenig", "uuid": "{c862cdd9-fcc8-4419-9fc7-e20db14b8fcb}", "links": {"self": {"href": "https://api.bitbucket.org/2.0/users/%7Bc862cdd9-fcc8-4419-9fc7-e20db14b8fcb%7D"}, "html": {"href": "https://bitbucket.org/%7Bc862cdd9-fcc8-4419-9fc7-e20db14b8fcb%7D/"}, "avatar": {"href": "https://avatar-management--avatars.us-west-2.prod.public.atl-paas.net/557058:095b1e12-74ed-4e20-b44f-2f0745b616e0/ca24bb11-4787-4b14-a20d-d91835e9bde2/128"}}, "nickname": "Nathan Koenig", "type": "user", "account_id": "557058:095b1e12-74ed-4e20-b44f-2f0745b616e0"}, "date": "2018-03-22T15:43:39.742715+00:00"}, "pull_request": {"type": "pullrequest", "id": 420, "links": {"self": {"href": "data/repositories/osrf/sdformat/pullrequests/420.json"}, "html": {"href": "#!/osrf/sdformat/pull-requests/420"}}, "title": "Load from string"}}, {"update": {"description": "Support loading from an SDF string.", "title": "Load from string", "destination": {"commit": {"hash": "652ce6cc1463", "type": "commit", "links": {"self": {"href": "data/repositories/osrf/sdformat/commit/652ce6cc1463.json"}, "html": {"href": "#!/osrf/sdformat/commits/652ce6cc1463"}}}, "repository": {"links": {"self": {"href": "data/repositories/osrf/sdformat.json"}, "html": {"href": "#!/osrf/sdformat"}, "avatar": {"href": "data/bytebucket.org/ravatar/{b6d52f9f-b070-41c0-807c-94af07ea375b}ts=1606789"}}, "type": "repository", "name": "sdformat", "full_name": "osrf/sdformat", "uuid": "{b6d52f9f-b070-41c0-807c-94af07ea375b}"}, "branch": {"name": "default"}}, "reason": "", "source": {"commit": {"hash": "2d030756b9a3", "type": "commit", "links": {"self": {"href": "data/repositories/osrf/sdformat/commit/2d030756b9a3.json"}, "html": {"href": "#!/osrf/sdformat/commits/2d030756b9a3"}}}, "repository": {"links": {"self": {"href": "data/repositories/osrf/sdformat.json"}, "html": {"href": "#!/osrf/sdformat"}, "avatar": {"href": "data/bytebucket.org/ravatar/{b6d52f9f-b070-41c0-807c-94af07ea375b}ts=1606789"}}, "type": "repository", "name": "sdformat", "full_name": "osrf/sdformat", "uuid": "{b6d52f9f-b070-41c0-807c-94af07ea375b}"}, "branch": {"name": "dom_load_string"}}, "state": "OPEN", "author": {"display_name": "Nate Koenig", "uuid": "{c862cdd9-fcc8-4419-9fc7-e20db14b8fcb}", "links": {"self": {"href": "https://api.bitbucket.org/2.0/users/%7Bc862cdd9-fcc8-4419-9fc7-e20db14b8fcb%7D"}, "html": {"href": "https://bitbucket.org/%7Bc862cdd9-fcc8-4419-9fc7-e20db14b8fcb%7D/"}, "avatar": {"href": "https://avatar-management--avatars.us-west-2.prod.public.atl-paas.net/557058:095b1e12-74ed-4e20-b44f-2f0745b616e0/ca24bb11-4787-4b14-a20d-d91835e9bde2/128"}}, "nickname": "Nathan Koenig", "type": "user", "account_id": "557058:095b1e12-74ed-4e20-b44f-2f0745b616e0"}, "date": "2018-03-22T15:43:03.417287+00:00"}, "pull_request": {"type": "pullrequest", "id": 420, "links": {"self": {"href": "data/repositories/osrf/sdformat/pullrequests/420.json"}, "html": {"href": "#!/osrf/sdformat/pull-requests/420"}}, "title": "Load from string"}}, {"update": {"description": "Support loading from an SDF string.", "title": "Load from string", "destination": {"commit": {"hash": "652ce6cc1463", "type": "commit", "links": {"self": {"href": "data/repositories/osrf/sdformat/commit/652ce6cc1463.json"}, "html": {"href": "#!/osrf/sdformat/commits/652ce6cc1463"}}}, "repository": {"links": {"self": {"href": "data/repositories/osrf/sdformat.json"}, "html": {"href": "#!/osrf/sdformat"}, "avatar": {"href": "data/bytebucket.org/ravatar/{b6d52f9f-b070-41c0-807c-94af07ea375b}ts=1606789"}}, "type": "repository", "name": "sdformat", "full_name": "osrf/sdformat", "uuid": "{b6d52f9f-b070-41c0-807c-94af07ea375b}"}, "branch": {"name": "default"}}, "reason": "", "source": {"commit": {"hash": "2d030756b9a3", "type": "commit", "links": {"self": {"href": "data/repositories/osrf/sdformat/commit/2d030756b9a3.json"}, "html": {"href": "#!/osrf/sdformat/commits/2d030756b9a3"}}}, "repository": {"links": {"self": {"href": "data/repositories/osrf/sdformat.json"}, "html": {"href": "#!/osrf/sdformat"}, "avatar": {"href": "data/bytebucket.org/ravatar/{b6d52f9f-b070-41c0-807c-94af07ea375b}ts=1606789"}}, "type": "repository", "name": "sdformat", "full_name": "osrf/sdformat", "uuid": "{b6d52f9f-b070-41c0-807c-94af07ea375b}"}, "branch": {"name": "dom_load_string"}}, "state": "OPEN", "author": {"display_name": "Nate Koenig", "uuid": "{c862cdd9-fcc8-4419-9fc7-e20db14b8fcb}", "links": {"self": {"href": "https://api.bitbucket.org/2.0/users/%7Bc862cdd9-fcc8-4419-9fc7-e20db14b8fcb%7D"}, "html": {"href": "https://bitbucket.org/%7Bc862cdd9-fcc8-4419-9fc7-e20db14b8fcb%7D/"}, "avatar": {"href": "https://avatar-management--avatars.us-west-2.prod.public.atl-paas.net/557058:095b1e12-74ed-4e20-b44f-2f0745b616e0/ca24bb11-4787-4b14-a20d-d91835e9bde2/128"}}, "nickname": "Nathan Koenig", "type": "user", "account_id": "557058:095b1e12-74ed-4e20-b44f-2f0745b616e0"}, "date": "2018-03-22T15:43:03.380666+00:00"}, "pull_request": {"type": "pullrequest", "id": 420, "links": {"self": {"href": "data/repositories/osrf/sdformat/pullrequests/420.json"}, "html": {"href": "#!/osrf/sdformat/pull-requests/420"}}, "title": "Load from string"}}]}