{"pagelen": 100, "values": [{"links": {"self": {"href": "data/repositories/osrf/sdformat/pullrequests/547/comments/106479145.json"}, "code": {"href": "https://api.bitbucket.org/2.0/repositories/osrf/sdformat/diff/mingfeisun/sdformat:f16b64336803..0b0a836f2b25?path=include%2Fsdf%2FActor.hh"}, "html": {"href": "#!/osrf/sdformat/pull-requests/547/_/diff#comment-106479145"}}, "deleted": false, "pullrequest": {"type": "pullrequest", "id": 547, "links": {"self": {"href": "data/repositories/osrf/sdformat/pullrequests/547.json"}, "html": {"href": "#!/osrf/sdformat/pull-requests/547"}}, "title": "add Actor parsing and tests"}, "content": {"raw": "Are you calling these functions `ActorStatic` because `Static` may be a reserved word? I tried changing it to `Static` and it compiled happily for me.", "markup": "markdown", "html": "<p>Are you calling these functions <code>ActorStatic</code> because <code>Static</code> may be a reserved word? I tried changing it to <code>Static</code> and it compiled happily for me.</p>", "type": "rendered"}, "created_on": "2019-06-20T13:55:44.387357+00:00", "user": {"display_name": "Louise Poubel", "uuid": "{5cfa2075-477b-4ded-bdb9-8d2479544ec4}", "links": {"self": {"href": "https://api.bitbucket.org/2.0/users/%7B5cfa2075-477b-4ded-bdb9-8d2479544ec4%7D"}, "html": {"href": "https://bitbucket.org/%7B5cfa2075-477b-4ded-bdb9-8d2479544ec4%7D/"}, "avatar": {"href": "https://avatar-management--avatars.us-west-2.prod.public.atl-paas.net/557058:6ff86fcb-b7ab-44a5-b8a6-f6d9cae8b6e8/7d903d90-c5ea-4182-b7ef-0d467e9e1c74/128"}}, "nickname": "chapulina", "type": "user", "account_id": "557058:6ff86fcb-b7ab-44a5-b8a6-f6d9cae8b6e8"}, "inline": {"to": 307, "from": null, "path": "include/sdf/Actor.hh"}, "updated_on": "2019-06-20T13:55:44.402106+00:00", "type": "pullrequest_comment", "id": 106479145}, {"links": {"self": {"href": "data/repositories/osrf/sdformat/pullrequests/547/comments/106481225.json"}, "code": {"href": "https://api.bitbucket.org/2.0/repositories/osrf/sdformat/diff/mingfeisun/sdformat:f16b64336803..0b0a836f2b25?path=include%2Fsdf%2FActor.hh"}, "html": {"href": "#!/osrf/sdformat/pull-requests/547/_/diff#comment-106481225"}}, "parent": {"id": 106479145, "links": {"self": {"href": "data/repositories/osrf/sdformat/pullrequests/547/comments/106479145.json"}, "html": {"href": "#!/osrf/sdformat/pull-requests/547/_/diff#comment-106479145"}}, "depth": 1}, "deleted": false, "pullrequest": {"type": "pullrequest", "id": 547, "links": {"self": {"href": "data/repositories/osrf/sdformat/pullrequests/547.json"}, "html": {"href": "#!/osrf/sdformat/pull-requests/547"}}, "title": "add Actor parsing and tests"}, "content": {"raw": "Yes. I am not sure whether using `Static` could cause any confusion here. So I explicitly use `ActorStatic`. I can change it back if `Static` appears to be more correct.", "markup": "markdown", "html": "<p>Yes. I am not sure whether using <code>Static</code> could cause any confusion here. So I explicitly use <code>ActorStatic</code>. I can change it back if <code>Static</code> appears to be more correct.</p>", "type": "rendered"}, "created_on": "2019-06-20T14:06:00.002471+00:00", "user": {"display_name": "mingfei sun", "uuid": "{1e5a944b-56e4-4808-b81d-d6de318feadc}", "links": {"self": {"href": "https://api.bitbucket.org/2.0/users/%7B1e5a944b-56e4-4808-b81d-d6de318feadc%7D"}, "html": {"href": "https://bitbucket.org/%7B1e5a944b-56e4-4808-b81d-d6de318feadc%7D/"}, "avatar": {"href": "data/secure.gravatar.com/avatar/a4be22d43d004c04e5f8fee72a65d214d=httpsavatar-management--avatars.us-west-2.prod.public.atl-paas.netinitialsMS-1.png"}}, "nickname": "mingfeisun", "type": "user", "account_id": "557058:ad32c2b0-bebb-403e-b385-c3c1f7aa1d09"}, "inline": {"to": 307, "from": null, "path": "include/sdf/Actor.hh"}, "updated_on": "2019-06-20T14:06:00.152528+00:00", "type": "pullrequest_comment", "id": 106481225}, {"links": {"self": {"href": "data/repositories/osrf/sdformat/pullrequests/547/comments/106481711.json"}, "code": {"href": "https://api.bitbucket.org/2.0/repositories/osrf/sdformat/diff/mingfeisun/sdformat:f16b64336803..0b0a836f2b25?path=include%2Fsdf%2FActor.hh"}, "html": {"href": "#!/osrf/sdformat/pull-requests/547/_/diff#comment-106481711"}}, "parent": {"id": 106481225, "links": {"self": {"href": "data/repositories/osrf/sdformat/pullrequests/547/comments/106481225.json"}, "html": {"href": "#!/osrf/sdformat/pull-requests/547/_/diff#comment-106481225"}}, "depth": 2}, "deleted": false, "pullrequest": {"type": "pullrequest", "id": 547, "links": {"self": {"href": "data/repositories/osrf/sdformat/pullrequests/547.json"}, "html": {"href": "#!/osrf/sdformat/pull-requests/547"}}, "title": "add Actor parsing and tests"}, "content": {"raw": "`sdf::Model` is using [Static()](#!/osrf/sdformat/src/08ea83caa185e305fcc5d21b80e0b388cf9901b0/include/sdf/Model.hh#lines-82), so I think it's good to be consistent here.", "markup": "markdown", "html": "<p><code>sdf::Model</code> is using <a data-is-external-link=\"true\" href=\"#!/osrf/sdformat/src/08ea83caa185e305fcc5d21b80e0b388cf9901b0/include/sdf/Model.hh#lines-82\" rel=\"nofollow\">Static()</a>, so I think it's good to be consistent here.</p>", "type": "rendered"}, "created_on": "2019-06-20T14:08:18.881847+00:00", "user": {"display_name": "Louise Poubel", "uuid": "{5cfa2075-477b-4ded-bdb9-8d2479544ec4}", "links": {"self": {"href": "https://api.bitbucket.org/2.0/users/%7B5cfa2075-477b-4ded-bdb9-8d2479544ec4%7D"}, "html": {"href": "https://bitbucket.org/%7B5cfa2075-477b-4ded-bdb9-8d2479544ec4%7D/"}, "avatar": {"href": "https://avatar-management--avatars.us-west-2.prod.public.atl-paas.net/557058:6ff86fcb-b7ab-44a5-b8a6-f6d9cae8b6e8/7d903d90-c5ea-4182-b7ef-0d467e9e1c74/128"}}, "nickname": "chapulina", "type": "user", "account_id": "557058:6ff86fcb-b7ab-44a5-b8a6-f6d9cae8b6e8"}, "inline": {"to": 307, "from": null, "path": "include/sdf/Actor.hh"}, "updated_on": "2019-06-20T14:08:18.897130+00:00", "type": "pullrequest_comment", "id": 106481711}, {"links": {"self": {"href": "data/repositories/osrf/sdformat/pullrequests/547/comments/106481824.json"}, "code": {"href": "https://api.bitbucket.org/2.0/repositories/osrf/sdformat/diff/mingfeisun/sdformat:f16b64336803..0b0a836f2b25?path=include%2Fsdf%2FActor.hh"}, "html": {"href": "#!/osrf/sdformat/pull-requests/547/_/diff#comment-106481824"}}, "parent": {"id": 106481711, "links": {"self": {"href": "data/repositories/osrf/sdformat/pullrequests/547/comments/106481711.json"}, "html": {"href": "#!/osrf/sdformat/pull-requests/547/_/diff#comment-106481711"}}, "depth": 3}, "deleted": false, "pullrequest": {"type": "pullrequest", "id": 547, "links": {"self": {"href": "data/repositories/osrf/sdformat/pullrequests/547.json"}, "html": {"href": "#!/osrf/sdformat/pull-requests/547"}}, "title": "add Actor parsing and tests"}, "content": {"raw": "Sure. Thanks for the pointing", "markup": "markdown", "html": "<p>Sure. Thanks for the pointing</p>", "type": "rendered"}, "created_on": "2019-06-20T14:08:58.365341+00:00", "user": {"display_name": "mingfei sun", "uuid": "{1e5a944b-56e4-4808-b81d-d6de318feadc}", "links": {"self": {"href": "https://api.bitbucket.org/2.0/users/%7B1e5a944b-56e4-4808-b81d-d6de318feadc%7D"}, "html": {"href": "https://bitbucket.org/%7B1e5a944b-56e4-4808-b81d-d6de318feadc%7D/"}, "avatar": {"href": "data/secure.gravatar.com/avatar/a4be22d43d004c04e5f8fee72a65d214d=httpsavatar-management--avatars.us-west-2.prod.public.atl-paas.netinitialsMS-1.png"}}, "nickname": "mingfeisun", "type": "user", "account_id": "557058:ad32c2b0-bebb-403e-b385-c3c1f7aa1d09"}, "inline": {"to": 307, "from": null, "path": "include/sdf/Actor.hh"}, "updated_on": "2019-06-20T14:08:58.515022+00:00", "type": "pullrequest_comment", "id": 106481824}, {"links": {"self": {"href": "data/repositories/osrf/sdformat/pullrequests/547/comments/106487301.json"}, "code": {"href": "https://api.bitbucket.org/2.0/repositories/osrf/sdformat/diff/mingfeisun/sdformat:f16b64336803..0b0a836f2b25?path=include%2Fsdf%2FActor.hh"}, "html": {"href": "#!/osrf/sdformat/pull-requests/547/_/diff#comment-106487301"}}, "parent": {"id": 106481711, "links": {"self": {"href": "data/repositories/osrf/sdformat/pullrequests/547/comments/106481711.json"}, "html": {"href": "#!/osrf/sdformat/pull-requests/547/_/diff#comment-106481711"}}, "depth": 3}, "deleted": true, "pullrequest": {"type": "pullrequest", "id": 547, "links": {"self": {"href": "data/repositories/osrf/sdformat/pullrequests/547.json"}, "html": {"href": "#!/osrf/sdformat/pull-requests/547"}}, "title": "add Actor parsing and tests"}, "content": {"raw": "", "markup": "markdown", "html": "", "type": "rendered"}, "created_on": "2019-06-20T14:38:47.424500+00:00", "user": {"display_name": "mingfei sun", "uuid": "{1e5a944b-56e4-4808-b81d-d6de318feadc}", "links": {"self": {"href": "https://api.bitbucket.org/2.0/users/%7B1e5a944b-56e4-4808-b81d-d6de318feadc%7D"}, "html": {"href": "https://bitbucket.org/%7B1e5a944b-56e4-4808-b81d-d6de318feadc%7D/"}, "avatar": {"href": "data/secure.gravatar.com/avatar/a4be22d43d004c04e5f8fee72a65d214d=httpsavatar-management--avatars.us-west-2.prod.public.atl-paas.netinitialsMS-1.png"}}, "nickname": "mingfeisun", "type": "user", "account_id": "557058:ad32c2b0-bebb-403e-b385-c3c1f7aa1d09"}, "inline": {"to": 307, "from": null, "path": "include/sdf/Actor.hh"}, "updated_on": "2019-06-20T14:40:26.197386+00:00", "type": "pullrequest_comment", "id": 106487301}, {"links": {"self": {"href": "data/repositories/osrf/sdformat/pullrequests/547/comments/106487801.json"}, "code": {"href": "https://api.bitbucket.org/2.0/repositories/osrf/sdformat/diff/mingfeisun/sdformat:f16b64336803..0b0a836f2b25?path=include%2Fsdf%2FActor.hh"}, "html": {"href": "#!/osrf/sdformat/pull-requests/547/_/diff#comment-106487801"}}, "parent": {"id": 106481711, "links": {"self": {"href": "data/repositories/osrf/sdformat/pullrequests/547/comments/106481711.json"}, "html": {"href": "#!/osrf/sdformat/pull-requests/547/_/diff#comment-106481711"}}, "depth": 3}, "deleted": false, "pullrequest": {"type": "pullrequest", "id": 547, "links": {"self": {"href": "data/repositories/osrf/sdformat/pullrequests/547.json"}, "html": {"href": "#!/osrf/sdformat/pull-requests/547"}}, "title": "add Actor parsing and tests"}, "content": {"raw": "I named it as `isStatic` in `ActorPrivate`, same as in `sdf::Model`.", "markup": "markdown", "html": "<p>I named it as <code>isStatic</code> in <code>ActorPrivate</code>, same as in <code>sdf::Model</code>.</p>", "type": "rendered"}, "created_on": "2019-06-20T14:41:35.672302+00:00", "user": {"display_name": "mingfei sun", "uuid": "{1e5a944b-56e4-4808-b81d-d6de318feadc}", "links": {"self": {"href": "https://api.bitbucket.org/2.0/users/%7B1e5a944b-56e4-4808-b81d-d6de318feadc%7D"}, "html": {"href": "https://bitbucket.org/%7B1e5a944b-56e4-4808-b81d-d6de318feadc%7D/"}, "avatar": {"href": "data/secure.gravatar.com/avatar/a4be22d43d004c04e5f8fee72a65d214d=httpsavatar-management--avatars.us-west-2.prod.public.atl-paas.netinitialsMS-1.png"}}, "nickname": "mingfeisun", "type": "user", "account_id": "557058:ad32c2b0-bebb-403e-b385-c3c1f7aa1d09"}, "inline": {"to": 307, "from": null, "path": "include/sdf/Actor.hh"}, "updated_on": "2019-06-20T14:41:35.947032+00:00", "type": "pullrequest_comment", "id": 106487801}, {"links": {"self": {"href": "data/repositories/osrf/sdformat/pullrequests/547/comments/106479490.json"}, "code": {"href": "https://api.bitbucket.org/2.0/repositories/osrf/sdformat/diff/mingfeisun/sdformat:f16b64336803..0b0a836f2b25?path=src%2FActor.cc"}, "html": {"href": "#!/osrf/sdformat/pull-requests/547/_/diff#comment-106479490"}}, "deleted": false, "pullrequest": {"type": "pullrequest", "id": 547, "links": {"self": {"href": "data/repositories/osrf/sdformat/pullrequests/547.json"}, "html": {"href": "#!/osrf/sdformat/pull-requests/547"}}, "title": "add Actor parsing and tests"}, "content": {"raw": "A reminder not to forget to use `camelCase` instead of `snake_case` for all variables (i.e. `skinFilename`)", "markup": "markdown", "html": "<p>A reminder not to forget to use <code>camelCase</code> instead of <code>snake_case</code> for all variables (i.e. <code>skinFilename</code>)</p>", "type": "rendered"}, "created_on": "2019-06-20T13:57:26.229736+00:00", "user": {"display_name": "Louise Poubel", "uuid": "{5cfa2075-477b-4ded-bdb9-8d2479544ec4}", "links": {"self": {"href": "https://api.bitbucket.org/2.0/users/%7B5cfa2075-477b-4ded-bdb9-8d2479544ec4%7D"}, "html": {"href": "https://bitbucket.org/%7B5cfa2075-477b-4ded-bdb9-8d2479544ec4%7D/"}, "avatar": {"href": "https://avatar-management--avatars.us-west-2.prod.public.atl-paas.net/557058:6ff86fcb-b7ab-44a5-b8a6-f6d9cae8b6e8/7d903d90-c5ea-4182-b7ef-0d467e9e1c74/128"}}, "nickname": "chapulina", "type": "user", "account_id": "557058:6ff86fcb-b7ab-44a5-b8a6-f6d9cae8b6e8"}, "inline": {"to": 84, "from": null, "path": "src/Actor.cc"}, "updated_on": "2019-06-20T13:57:26.239869+00:00", "type": "pullrequest_comment", "id": 106479490}, {"links": {"self": {"href": "data/repositories/osrf/sdformat/pullrequests/547/comments/106481310.json"}, "code": {"href": "https://api.bitbucket.org/2.0/repositories/osrf/sdformat/diff/mingfeisun/sdformat:f16b64336803..0b0a836f2b25?path=src%2FActor.cc"}, "html": {"href": "#!/osrf/sdformat/pull-requests/547/_/diff#comment-106481310"}}, "parent": {"id": 106479490, "links": {"self": {"href": "data/repositories/osrf/sdformat/pullrequests/547/comments/106479490.json"}, "html": {"href": "#!/osrf/sdformat/pull-requests/547/_/diff#comment-106479490"}}, "depth": 1}, "deleted": false, "pullrequest": {"type": "pullrequest", "id": 547, "links": {"self": {"href": "data/repositories/osrf/sdformat/pullrequests/547.json"}, "html": {"href": "#!/osrf/sdformat/pull-requests/547"}}, "title": "add Actor parsing and tests"}, "content": {"raw": "Thanks. :sweat_smile: ", "markup": "markdown", "html": "<p>Thanks. <img class=\"emoji\" src=\"data/pf-emoji-service--cdn.us-east-1.prod.public.atl-paas.net/standard/551c9814-1d37-4573-819d-afab3afeaf32/48x48/1f605.png\" alt=\"\ud83d\ude05\" title=\":sweat_smile:\" data-emoji-short-name=\":sweat_smile:\" /> </p>", "type": "rendered"}, "created_on": "2019-06-20T14:06:21.752502+00:00", "user": {"display_name": "mingfei sun", "uuid": "{1e5a944b-56e4-4808-b81d-d6de318feadc}", "links": {"self": {"href": "https://api.bitbucket.org/2.0/users/%7B1e5a944b-56e4-4808-b81d-d6de318feadc%7D"}, "html": {"href": "https://bitbucket.org/%7B1e5a944b-56e4-4808-b81d-d6de318feadc%7D/"}, "avatar": {"href": "data/secure.gravatar.com/avatar/a4be22d43d004c04e5f8fee72a65d214d=httpsavatar-management--avatars.us-west-2.prod.public.atl-paas.netinitialsMS-1.png"}}, "nickname": "mingfeisun", "type": "user", "account_id": "557058:ad32c2b0-bebb-403e-b385-c3c1f7aa1d09"}, "inline": {"to": 84, "from": null, "path": "src/Actor.cc"}, "updated_on": "2019-06-20T14:06:21.866203+00:00", "type": "pullrequest_comment", "id": 106481310}, {"links": {"self": {"href": "data/repositories/osrf/sdformat/pullrequests/547/comments/106479969.json"}, "code": {"href": "https://api.bitbucket.org/2.0/repositories/osrf/sdformat/diff/mingfeisun/sdformat:f16b64336803..0b0a836f2b25?path=src%2FActor.cc"}, "html": {"href": "#!/osrf/sdformat/pull-requests/547/_/diff#comment-106479969"}}, "deleted": false, "pullrequest": {"type": "pullrequest", "id": 547, "links": {"self": {"href": "data/repositories/osrf/sdformat/pullrequests/547.json"}, "html": {"href": "#!/osrf/sdformat/pull-requests/547"}}, "title": "add Actor parsing and tests"}, "content": {"raw": "Note that the `<actor>` tag can also contain [links, joints and plugins](#!/osrf/sdformat/src/08ea83caa185e305fcc5d21b80e0b388cf9901b0/sdf/1.6/actor.sdf#lines-87), so we need to expose those through the API as well. ", "markup": "markdown", "html": "<p>Note that the <code>&lt;actor&gt;</code> tag can also contain <a data-is-external-link=\"true\" href=\"#!/osrf/sdformat/src/08ea83caa185e305fcc5d21b80e0b388cf9901b0/sdf/1.6/actor.sdf#lines-87\" rel=\"nofollow\">links, joints and plugins</a>, so we need to expose those through the API as well. </p>", "type": "rendered"}, "created_on": "2019-06-20T13:59:44.798277+00:00", "user": {"display_name": "Louise Poubel", "uuid": "{5cfa2075-477b-4ded-bdb9-8d2479544ec4}", "links": {"self": {"href": "https://api.bitbucket.org/2.0/users/%7B5cfa2075-477b-4ded-bdb9-8d2479544ec4%7D"}, "html": {"href": "https://bitbucket.org/%7B5cfa2075-477b-4ded-bdb9-8d2479544ec4%7D/"}, "avatar": {"href": "https://avatar-management--avatars.us-west-2.prod.public.atl-paas.net/557058:6ff86fcb-b7ab-44a5-b8a6-f6d9cae8b6e8/7d903d90-c5ea-4182-b7ef-0d467e9e1c74/128"}}, "nickname": "chapulina", "type": "user", "account_id": "557058:6ff86fcb-b7ab-44a5-b8a6-f6d9cae8b6e8"}, "inline": {"to": 106, "from": null, "path": "src/Actor.cc"}, "updated_on": "2019-06-20T13:59:44.809330+00:00", "type": "pullrequest_comment", "id": 106479969}, {"links": {"self": {"href": "data/repositories/osrf/sdformat/pullrequests/547/comments/106481502.json"}, "code": {"href": "https://api.bitbucket.org/2.0/repositories/osrf/sdformat/diff/mingfeisun/sdformat:f16b64336803..0b0a836f2b25?path=src%2FActor.cc"}, "html": {"href": "#!/osrf/sdformat/pull-requests/547/_/diff#comment-106481502"}}, "parent": {"id": 106479969, "links": {"self": {"href": "data/repositories/osrf/sdformat/pullrequests/547/comments/106479969.json"}, "html": {"href": "#!/osrf/sdformat/pull-requests/547/_/diff#comment-106479969"}}, "depth": 1}, "deleted": false, "pullrequest": {"type": "pullrequest", "id": 547, "links": {"self": {"href": "data/repositories/osrf/sdformat/pullrequests/547.json"}, "html": {"href": "#!/osrf/sdformat/pull-requests/547"}}, "title": "add Actor parsing and tests"}, "content": {"raw": "Sure. Do we need to modify the `sdf` file as well?", "markup": "markdown", "html": "<p>Sure. Do we need to modify the <code>sdf</code> file as well?</p>", "type": "rendered"}, "created_on": "2019-06-20T14:07:10.099758+00:00", "user": {"display_name": "mingfei sun", "uuid": "{1e5a944b-56e4-4808-b81d-d6de318feadc}", "links": {"self": {"href": "https://api.bitbucket.org/2.0/users/%7B1e5a944b-56e4-4808-b81d-d6de318feadc%7D"}, "html": {"href": "https://bitbucket.org/%7B1e5a944b-56e4-4808-b81d-d6de318feadc%7D/"}, "avatar": {"href": "data/secure.gravatar.com/avatar/a4be22d43d004c04e5f8fee72a65d214d=httpsavatar-management--avatars.us-west-2.prod.public.atl-paas.netinitialsMS-1.png"}}, "nickname": "mingfeisun", "type": "user", "account_id": "557058:ad32c2b0-bebb-403e-b385-c3c1f7aa1d09"}, "inline": {"to": 106, "from": null, "path": "src/Actor.cc"}, "updated_on": "2019-06-20T14:07:10.252616+00:00", "type": "pullrequest_comment", "id": 106481502}, {"links": {"self": {"href": "data/repositories/osrf/sdformat/pullrequests/547/comments/106481927.json"}, "code": {"href": "https://api.bitbucket.org/2.0/repositories/osrf/sdformat/diff/mingfeisun/sdformat:f16b64336803..0b0a836f2b25?path=src%2FActor.cc"}, "html": {"href": "#!/osrf/sdformat/pull-requests/547/_/diff#comment-106481927"}}, "parent": {"id": 106481502, "links": {"self": {"href": "data/repositories/osrf/sdformat/pullrequests/547/comments/106481502.json"}, "html": {"href": "#!/osrf/sdformat/pull-requests/547/_/diff#comment-106481502"}}, "depth": 2}, "deleted": false, "pullrequest": {"type": "pullrequest", "id": 547, "links": {"self": {"href": "data/repositories/osrf/sdformat/pullrequests/547.json"}, "html": {"href": "#!/osrf/sdformat/pull-requests/547"}}, "title": "add Actor parsing and tests"}, "content": {"raw": "If you check the link on the comment above, you can see that they're already in the `actor.sdf` file, using `<include>`", "markup": "markdown", "html": "<p>If you check the link on the comment above, you can see that they're already in the <code>actor.sdf</code> file, using <code>&lt;include&gt;</code></p>", "type": "rendered"}, "created_on": "2019-06-20T14:09:27.982310+00:00", "user": {"display_name": "Louise Poubel", "uuid": "{5cfa2075-477b-4ded-bdb9-8d2479544ec4}", "links": {"self": {"href": "https://api.bitbucket.org/2.0/users/%7B5cfa2075-477b-4ded-bdb9-8d2479544ec4%7D"}, "html": {"href": "https://bitbucket.org/%7B5cfa2075-477b-4ded-bdb9-8d2479544ec4%7D/"}, "avatar": {"href": "https://avatar-management--avatars.us-west-2.prod.public.atl-paas.net/557058:6ff86fcb-b7ab-44a5-b8a6-f6d9cae8b6e8/7d903d90-c5ea-4182-b7ef-0d467e9e1c74/128"}}, "nickname": "chapulina", "type": "user", "account_id": "557058:6ff86fcb-b7ab-44a5-b8a6-f6d9cae8b6e8"}, "inline": {"to": 106, "from": null, "path": "src/Actor.cc"}, "updated_on": "2019-06-20T14:09:50.657979+00:00", "type": "pullrequest_comment", "id": 106481927}, {"links": {"self": {"href": "data/repositories/osrf/sdformat/pullrequests/547/comments/106482321.json"}, "code": {"href": "https://api.bitbucket.org/2.0/repositories/osrf/sdformat/diff/mingfeisun/sdformat:f16b64336803..0b0a836f2b25?path=src%2FActor.cc"}, "html": {"href": "#!/osrf/sdformat/pull-requests/547/_/diff#comment-106482321"}}, "parent": {"id": 106481927, "links": {"self": {"href": "data/repositories/osrf/sdformat/pullrequests/547/comments/106481927.json"}, "html": {"href": "#!/osrf/sdformat/pull-requests/547/_/diff#comment-106481927"}}, "depth": 3}, "deleted": false, "pullrequest": {"type": "pullrequest", "id": 547, "links": {"self": {"href": "data/repositories/osrf/sdformat/pullrequests/547.json"}, "html": {"href": "#!/osrf/sdformat/pull-requests/547"}}, "title": "add Actor parsing and tests"}, "content": {"raw": "Oh. Sorry that I didn\u2019t notice that. Thanks for reminding.", "markup": "markdown", "html": "<p>Oh. Sorry that I didn\u2019t notice that. Thanks for reminding.</p>", "type": "rendered"}, "created_on": "2019-06-20T14:11:38.780162+00:00", "user": {"display_name": "mingfei sun", "uuid": "{1e5a944b-56e4-4808-b81d-d6de318feadc}", "links": {"self": {"href": "https://api.bitbucket.org/2.0/users/%7B1e5a944b-56e4-4808-b81d-d6de318feadc%7D"}, "html": {"href": "https://bitbucket.org/%7B1e5a944b-56e4-4808-b81d-d6de318feadc%7D/"}, "avatar": {"href": "data/secure.gravatar.com/avatar/a4be22d43d004c04e5f8fee72a65d214d=httpsavatar-management--avatars.us-west-2.prod.public.atl-paas.netinitialsMS-1.png"}}, "nickname": "mingfeisun", "type": "user", "account_id": "557058:ad32c2b0-bebb-403e-b385-c3c1f7aa1d09"}, "inline": {"to": 106, "from": null, "path": "src/Actor.cc"}, "updated_on": "2019-06-20T14:11:38.934954+00:00", "type": "pullrequest_comment", "id": 106482321}, {"links": {"self": {"href": "data/repositories/osrf/sdformat/pullrequests/547/comments/106555301.json"}, "code": {"href": "https://api.bitbucket.org/2.0/repositories/osrf/sdformat/diff/mingfeisun/sdformat:e83a575ab76d..0b0a836f2b25?path=src%2FActor.cc"}, "html": {"href": "#!/osrf/sdformat/pull-requests/547/_/diff#comment-106555301"}}, "parent": {"id": 106479969, "links": {"self": {"href": "data/repositories/osrf/sdformat/pullrequests/547/comments/106479969.json"}, "html": {"href": "#!/osrf/sdformat/pull-requests/547/_/diff#comment-106479969"}}, "depth": 1}, "deleted": false, "pullrequest": {"type": "pullrequest", "id": 547, "links": {"self": {"href": "data/repositories/osrf/sdformat/pullrequests/547.json"}, "html": {"href": "#!/osrf/sdformat/pull-requests/547"}}, "title": "add Actor parsing and tests"}, "content": {"raw": "I checked the other codes in `include/sdf` and in `src`. It seems that the `plugin` tag has not been parsed yet. There is not `plugin.cc` and `plugin.hh`. The `sdf` file that contains `<plugin>`, e.g., `sdf::sensor` and `sdf::model`, does not have the `plugin` or equivalent members.", "markup": "markdown", "html": "<p>I checked the other codes in <code>include/sdf</code> and in <code>src</code>. It seems that the <code>plugin</code> tag has not been parsed yet. There is not <code>plugin.cc</code> and <code>plugin.hh</code>. The <code>sdf</code> file that contains <code>&lt;plugin&gt;</code>, e.g., <code>sdf::sensor</code> and <code>sdf::model</code>, does not have the <code>plugin</code> or equivalent members.</p>", "type": "rendered"}, "created_on": "2019-06-21T03:45:00.064387+00:00", "user": {"display_name": "mingfei sun", "uuid": "{1e5a944b-56e4-4808-b81d-d6de318feadc}", "links": {"self": {"href": "https://api.bitbucket.org/2.0/users/%7B1e5a944b-56e4-4808-b81d-d6de318feadc%7D"}, "html": {"href": "https://bitbucket.org/%7B1e5a944b-56e4-4808-b81d-d6de318feadc%7D/"}, "avatar": {"href": "data/secure.gravatar.com/avatar/a4be22d43d004c04e5f8fee72a65d214d=httpsavatar-management--avatars.us-west-2.prod.public.atl-paas.netinitialsMS-1.png"}}, "nickname": "mingfeisun", "type": "user", "account_id": "557058:ad32c2b0-bebb-403e-b385-c3c1f7aa1d09"}, "inline": {"to": 106, "from": null, "path": "src/Actor.cc"}, "updated_on": "2019-06-21T03:45:00.371698+00:00", "type": "pullrequest_comment", "id": 106555301}, {"links": {"self": {"href": "data/repositories/osrf/sdformat/pullrequests/547/comments/106641115.json"}, "code": {"href": "https://api.bitbucket.org/2.0/repositories/osrf/sdformat/diff/mingfeisun/sdformat:ed9e457a354c..0b0a836f2b25?path=src%2FActor.cc"}, "html": {"href": "#!/osrf/sdformat/pull-requests/547/_/diff#comment-106641115"}}, "parent": {"id": 106555301, "links": {"self": {"href": "data/repositories/osrf/sdformat/pullrequests/547/comments/106555301.json"}, "html": {"href": "#!/osrf/sdformat/pull-requests/547/_/diff#comment-106555301"}}, "depth": 2}, "deleted": false, "pullrequest": {"type": "pullrequest", "id": 547, "links": {"self": {"href": "data/repositories/osrf/sdformat/pullrequests/547.json"}, "html": {"href": "#!/osrf/sdformat/pull-requests/547"}}, "title": "add Actor parsing and tests"}, "content": {"raw": "Oh yes, sorry for the misleading comment. It's ok to leave plugin out for now; we're getting it from `Element`.", "markup": "markdown", "html": "<p>Oh yes, sorry for the misleading comment. It's ok to leave plugin out for now; we're getting it from <code>Element</code>.</p>", "type": "rendered"}, "created_on": "2019-06-21T15:06:43.346186+00:00", "user": {"display_name": "Louise Poubel", "uuid": "{5cfa2075-477b-4ded-bdb9-8d2479544ec4}", "links": {"self": {"href": "https://api.bitbucket.org/2.0/users/%7B5cfa2075-477b-4ded-bdb9-8d2479544ec4%7D"}, "html": {"href": "https://bitbucket.org/%7B5cfa2075-477b-4ded-bdb9-8d2479544ec4%7D/"}, "avatar": {"href": "https://avatar-management--avatars.us-west-2.prod.public.atl-paas.net/557058:6ff86fcb-b7ab-44a5-b8a6-f6d9cae8b6e8/7d903d90-c5ea-4182-b7ef-0d467e9e1c74/128"}}, "nickname": "chapulina", "type": "user", "account_id": "557058:6ff86fcb-b7ab-44a5-b8a6-f6d9cae8b6e8"}, "inline": {"to": 106, "from": null, "path": "src/Actor.cc"}, "updated_on": "2019-06-21T15:06:43.360584+00:00", "type": "pullrequest_comment", "id": 106641115}, {"links": {"self": {"href": "data/repositories/osrf/sdformat/pullrequests/547/comments/106556415.json"}, "code": {"href": "https://api.bitbucket.org/2.0/repositories/osrf/sdformat/diff/mingfeisun/sdformat:e83a575ab76d..0b0a836f2b25?path=src%2FActor.cc"}, "html": {"href": "#!/osrf/sdformat/pull-requests/547/_/diff#comment-106556415"}}, "parent": {"id": 106479969, "links": {"self": {"href": "data/repositories/osrf/sdformat/pullrequests/547/comments/106479969.json"}, "html": {"href": "#!/osrf/sdformat/pull-requests/547/_/diff#comment-106479969"}}, "depth": 1}, "deleted": false, "pullrequest": {"type": "pullrequest", "id": 547, "links": {"self": {"href": "data/repositories/osrf/sdformat/pullrequests/547.json"}, "html": {"href": "#!/osrf/sdformat/pull-requests/547"}}, "title": "add Actor parsing and tests"}, "content": {"raw": "I am not sure but I guess the `links` and `joints` in `Actor` are supposed to be embedded in the animation or skin file. The `links` and `joints` are to describe the actor skeleton like a robot, right? Should we parse them in the `Actor.cc` and `Actor.hh`? Or we can parse them in the `Animation` ? ", "markup": "markdown", "html": "<p>I am not sure but I guess the <code>links</code> and <code>joints</code> in <code>Actor</code> are supposed to be embedded in the animation or skin file. The <code>links</code> and <code>joints</code> are to describe the actor skeleton like a robot, right? Should we parse them in the <code>Actor.cc</code> and <code>Actor.hh</code>? Or we can parse them in the <code>Animation</code> ? </p>", "type": "rendered"}, "created_on": "2019-06-21T04:08:51.326865+00:00", "user": {"display_name": "mingfei sun", "uuid": "{1e5a944b-56e4-4808-b81d-d6de318feadc}", "links": {"self": {"href": "https://api.bitbucket.org/2.0/users/%7B1e5a944b-56e4-4808-b81d-d6de318feadc%7D"}, "html": {"href": "https://bitbucket.org/%7B1e5a944b-56e4-4808-b81d-d6de318feadc%7D/"}, "avatar": {"href": "data/secure.gravatar.com/avatar/a4be22d43d004c04e5f8fee72a65d214d=httpsavatar-management--avatars.us-west-2.prod.public.atl-paas.netinitialsMS-1.png"}}, "nickname": "mingfeisun", "type": "user", "account_id": "557058:ad32c2b0-bebb-403e-b385-c3c1f7aa1d09"}, "inline": {"to": 106, "from": null, "path": "src/Actor.cc"}, "updated_on": "2019-06-21T04:08:51.611097+00:00", "type": "pullrequest_comment", "id": 106556415}, {"links": {"self": {"href": "data/repositories/osrf/sdformat/pullrequests/547/comments/106648445.json"}, "code": {"href": "https://api.bitbucket.org/2.0/repositories/osrf/sdformat/diff/mingfeisun/sdformat:ed9e457a354c..0b0a836f2b25?path=src%2FActor.cc"}, "html": {"href": "#!/osrf/sdformat/pull-requests/547/_/diff#comment-106648445"}}, "parent": {"id": 106556415, "links": {"self": {"href": "data/repositories/osrf/sdformat/pullrequests/547/comments/106556415.json"}, "html": {"href": "#!/osrf/sdformat/pull-requests/547/_/diff#comment-106556415"}}, "depth": 2}, "deleted": false, "pullrequest": {"type": "pullrequest", "id": 547, "links": {"self": {"href": "data/repositories/osrf/sdformat/pullrequests/547.json"}, "html": {"href": "#!/osrf/sdformat/pull-requests/547"}}, "title": "add Actor parsing and tests"}, "content": {"raw": "On Gazebo classic, Actor is not just a class for animation. It's more like an extension to models, so it can also have links and joints. So they're not tied to the animation or skin, they're directly under the `<actor>`. See [this example](http://gazebosim.org/tutorials?tut=actor&cat=build_robot#Worldexplained). Whether this is useful is a valid question though. I actually suspect that actor joints are useless, because neither physics nor the animation may be acting on them. We could consider decoupling the scripting of model trajectories from skeleton animation. \n\nSo feel free to leave links and joints out for now while we get skeleton animations to work. Once we have that working, we can revisit the idea of scripting link motions and see if they still fit well within actors. Sounds good?", "markup": "markdown", "html": "<p>On Gazebo classic, Actor is not just a class for animation. It's more like an extension to models, so it can also have links and joints. So they're not tied to the animation or skin, they're directly under the <code>&lt;actor&gt;</code>. See <a data-is-external-link=\"true\" href=\"http://gazebosim.org/tutorials?tut=actor&amp;cat=build_robot#Worldexplained\" rel=\"nofollow\">this example</a>. Whether this is useful is a valid question though. I actually suspect that actor joints are useless, because neither physics nor the animation may be acting on them. We could consider decoupling the scripting of model trajectories from skeleton animation. </p>\n<p>So feel free to leave links and joints out for now while we get skeleton animations to work. Once we have that working, we can revisit the idea of scripting link motions and see if they still fit well within actors. Sounds good?</p>", "type": "rendered"}, "created_on": "2019-06-21T15:57:28.388105+00:00", "user": {"display_name": "Louise Poubel", "uuid": "{5cfa2075-477b-4ded-bdb9-8d2479544ec4}", "links": {"self": {"href": "https://api.bitbucket.org/2.0/users/%7B5cfa2075-477b-4ded-bdb9-8d2479544ec4%7D"}, "html": {"href": "https://bitbucket.org/%7B5cfa2075-477b-4ded-bdb9-8d2479544ec4%7D/"}, "avatar": {"href": "https://avatar-management--avatars.us-west-2.prod.public.atl-paas.net/557058:6ff86fcb-b7ab-44a5-b8a6-f6d9cae8b6e8/7d903d90-c5ea-4182-b7ef-0d467e9e1c74/128"}}, "nickname": "chapulina", "type": "user", "account_id": "557058:6ff86fcb-b7ab-44a5-b8a6-f6d9cae8b6e8"}, "inline": {"to": 106, "from": null, "path": "src/Actor.cc"}, "updated_on": "2019-06-21T15:57:28.401818+00:00", "type": "pullrequest_comment", "id": 106648445}, {"links": {"self": {"href": "data/repositories/osrf/sdformat/pullrequests/547/comments/106685060.json"}, "code": {"href": "https://api.bitbucket.org/2.0/repositories/osrf/sdformat/diff/mingfeisun/sdformat:ed9e457a354c..0b0a836f2b25?path=src%2FActor.cc"}, "html": {"href": "#!/osrf/sdformat/pull-requests/547/_/diff#comment-106685060"}}, "parent": {"id": 106648445, "links": {"self": {"href": "data/repositories/osrf/sdformat/pullrequests/547/comments/106648445.json"}, "html": {"href": "#!/osrf/sdformat/pull-requests/547/_/diff#comment-106648445"}}, "depth": 3}, "deleted": false, "pullrequest": {"type": "pullrequest", "id": 547, "links": {"self": {"href": "data/repositories/osrf/sdformat/pullrequests/547.json"}, "html": {"href": "#!/osrf/sdformat/pull-requests/547"}}, "title": "add Actor parsing and tests"}, "content": {"raw": "Yes, it\u2019s good for me. Thanks for pointing to the example", "markup": "markdown", "html": "<p>Yes, it\u2019s good for me. Thanks for pointing to the example</p>", "type": "rendered"}, "created_on": "2019-06-22T01:50:23.887397+00:00", "user": {"display_name": "mingfei sun", "uuid": "{1e5a944b-56e4-4808-b81d-d6de318feadc}", "links": {"self": {"href": "https://api.bitbucket.org/2.0/users/%7B1e5a944b-56e4-4808-b81d-d6de318feadc%7D"}, "html": {"href": "https://bitbucket.org/%7B1e5a944b-56e4-4808-b81d-d6de318feadc%7D/"}, "avatar": {"href": "data/secure.gravatar.com/avatar/a4be22d43d004c04e5f8fee72a65d214d=httpsavatar-management--avatars.us-west-2.prod.public.atl-paas.netinitialsMS-1.png"}}, "nickname": "mingfeisun", "type": "user", "account_id": "557058:ad32c2b0-bebb-403e-b385-c3c1f7aa1d09"}, "inline": {"to": 106, "from": null, "path": "src/Actor.cc"}, "updated_on": "2019-06-22T01:50:24.166021+00:00", "type": "pullrequest_comment", "id": 106685060}, {"links": {"self": {"href": "data/repositories/osrf/sdformat/pullrequests/547/comments/106480386.json"}, "code": {"href": "https://api.bitbucket.org/2.0/repositories/osrf/sdformat/diff/mingfeisun/sdformat:f16b64336803..0b0a836f2b25?path=include%2Fsdf%2FActor.hh"}, "html": {"href": "#!/osrf/sdformat/pull-requests/547/_/diff#comment-106480386"}}, "deleted": false, "pullrequest": {"type": "pullrequest", "id": 547, "links": {"self": {"href": "data/repositories/osrf/sdformat/pullrequests/547.json"}, "html": {"href": "#!/osrf/sdformat/pull-requests/547"}}, "title": "add Actor parsing and tests"}, "content": {"raw": "I think you probably copied the pattern in `sdf::Light`, but I think this copy function is not needed since we already have the copy constructor and copy assignment operator.", "markup": "markdown", "html": "<p>I think you probably copied the pattern in <code>sdf::Light</code>, but I think this copy function is not needed since we already have the copy constructor and copy assignment operator.</p>", "type": "rendered"}, "created_on": "2019-06-20T14:01:51.808083+00:00", "user": {"display_name": "Louise Poubel", "uuid": "{5cfa2075-477b-4ded-bdb9-8d2479544ec4}", "links": {"self": {"href": "https://api.bitbucket.org/2.0/users/%7B5cfa2075-477b-4ded-bdb9-8d2479544ec4%7D"}, "html": {"href": "https://bitbucket.org/%7B5cfa2075-477b-4ded-bdb9-8d2479544ec4%7D/"}, "avatar": {"href": "https://avatar-management--avatars.us-west-2.prod.public.atl-paas.net/557058:6ff86fcb-b7ab-44a5-b8a6-f6d9cae8b6e8/7d903d90-c5ea-4182-b7ef-0d467e9e1c74/128"}}, "nickname": "chapulina", "type": "user", "account_id": "557058:6ff86fcb-b7ab-44a5-b8a6-f6d9cae8b6e8"}, "inline": {"to": 287, "from": null, "path": "include/sdf/Actor.hh"}, "updated_on": "2019-06-20T14:01:51.827917+00:00", "type": "pullrequest_comment", "id": 106480386}, {"links": {"self": {"href": "data/repositories/osrf/sdformat/pullrequests/547/comments/106480903.json"}, "code": {"href": "https://api.bitbucket.org/2.0/repositories/osrf/sdformat/diff/mingfeisun/sdformat:f16b64336803..0b0a836f2b25?path=include%2Fsdf%2FActor.hh"}, "html": {"href": "#!/osrf/sdformat/pull-requests/547/_/diff#comment-106480903"}}, "parent": {"id": 106480386, "links": {"self": {"href": "data/repositories/osrf/sdformat/pullrequests/547/comments/106480386.json"}, "html": {"href": "#!/osrf/sdformat/pull-requests/547/_/diff#comment-106480386"}}, "depth": 1}, "deleted": false, "pullrequest": {"type": "pullrequest", "id": 547, "links": {"self": {"href": "data/repositories/osrf/sdformat/pullrequests/547.json"}, "html": {"href": "#!/osrf/sdformat/pull-requests/547"}}, "title": "add Actor parsing and tests"}, "content": {"raw": "Sure. I can delete it.", "markup": "markdown", "html": "<p>Sure. I can delete it.</p>", "type": "rendered"}, "created_on": "2019-06-20T14:04:38.042468+00:00", "user": {"display_name": "mingfei sun", "uuid": "{1e5a944b-56e4-4808-b81d-d6de318feadc}", "links": {"self": {"href": "https://api.bitbucket.org/2.0/users/%7B1e5a944b-56e4-4808-b81d-d6de318feadc%7D"}, "html": {"href": "https://bitbucket.org/%7B1e5a944b-56e4-4808-b81d-d6de318feadc%7D/"}, "avatar": {"href": "data/secure.gravatar.com/avatar/a4be22d43d004c04e5f8fee72a65d214d=httpsavatar-management--avatars.us-west-2.prod.public.atl-paas.netinitialsMS-1.png"}}, "nickname": "mingfeisun", "type": "user", "account_id": "557058:ad32c2b0-bebb-403e-b385-c3c1f7aa1d09"}, "inline": {"to": 287, "from": null, "path": "include/sdf/Actor.hh"}, "updated_on": "2019-06-20T14:04:38.203432+00:00", "type": "pullrequest_comment", "id": 106480903}, {"links": {"self": {"href": "data/repositories/osrf/sdformat/pullrequests/547/comments/106486848.json"}, "code": {"href": "https://api.bitbucket.org/2.0/repositories/osrf/sdformat/diff/mingfeisun/sdformat:f16b64336803..0b0a836f2b25?path=include%2Fsdf%2FActor.hh"}, "html": {"href": "#!/osrf/sdformat/pull-requests/547/_/diff#comment-106486848"}}, "parent": {"id": 106480386, "links": {"self": {"href": "data/repositories/osrf/sdformat/pullrequests/547/comments/106480386.json"}, "html": {"href": "#!/osrf/sdformat/pull-requests/547/_/diff#comment-106480386"}}, "depth": 1}, "deleted": false, "pullrequest": {"type": "pullrequest", "id": 547, "links": {"self": {"href": "data/repositories/osrf/sdformat/pullrequests/547.json"}, "html": {"href": "#!/osrf/sdformat/pull-requests/547"}}, "title": "add Actor parsing and tests"}, "content": {"raw": "Oh, this `copyFrom` is to reduce the repeated codes I guess. `CopyFrom` is to assign values to the `dataPtr`.", "markup": "markdown", "html": "<p>Oh, this <code>copyFrom</code> is to reduce the repeated codes I guess. <code>CopyFrom</code> is to assign values to the <code>dataPtr</code>.</p>", "type": "rendered"}, "created_on": "2019-06-20T14:36:23.765779+00:00", "user": {"display_name": "mingfei sun", "uuid": "{1e5a944b-56e4-4808-b81d-d6de318feadc}", "links": {"self": {"href": "https://api.bitbucket.org/2.0/users/%7B1e5a944b-56e4-4808-b81d-d6de318feadc%7D"}, "html": {"href": "https://bitbucket.org/%7B1e5a944b-56e4-4808-b81d-d6de318feadc%7D/"}, "avatar": {"href": "data/secure.gravatar.com/avatar/a4be22d43d004c04e5f8fee72a65d214d=httpsavatar-management--avatars.us-west-2.prod.public.atl-paas.netinitialsMS-1.png"}}, "nickname": "mingfeisun", "type": "user", "account_id": "557058:ad32c2b0-bebb-403e-b385-c3c1f7aa1d09"}, "inline": {"to": 287, "from": null, "path": "include/sdf/Actor.hh"}, "updated_on": "2019-06-20T14:36:24.046059+00:00", "type": "pullrequest_comment", "id": 106486848}, {"links": {"self": {"href": "data/repositories/osrf/sdformat/pullrequests/547/comments/106494111.json"}, "code": {"href": "https://api.bitbucket.org/2.0/repositories/osrf/sdformat/diff/mingfeisun/sdformat:e83a575ab76d..0b0a836f2b25?path=include%2Fsdf%2FActor.hh"}, "html": {"href": "#!/osrf/sdformat/pull-requests/547/_/diff#comment-106494111"}}, "parent": {"id": 106486848, "links": {"self": {"href": "data/repositories/osrf/sdformat/pullrequests/547/comments/106486848.json"}, "html": {"href": "#!/osrf/sdformat/pull-requests/547/_/diff#comment-106486848"}}, "depth": 2}, "deleted": false, "pullrequest": {"type": "pullrequest", "id": 547, "links": {"self": {"href": "data/repositories/osrf/sdformat/pullrequests/547.json"}, "html": {"href": "#!/osrf/sdformat/pull-requests/547"}}, "title": "add Actor parsing and tests"}, "content": {"raw": "Oh sorry! It's ok to leave it if it's useful then :sweat_smile: ", "markup": "markdown", "html": "<p>Oh sorry! It's ok to leave it if it's useful then <img class=\"emoji\" src=\"data/pf-emoji-service--cdn.us-east-1.prod.public.atl-paas.net/standard/551c9814-1d37-4573-819d-afab3afeaf32/48x48/1f605.png\" alt=\"\ud83d\ude05\" title=\":sweat_smile:\" data-emoji-short-name=\":sweat_smile:\" /> </p>", "type": "rendered"}, "created_on": "2019-06-20T15:16:23.664831+00:00", "user": {"display_name": "Louise Poubel", "uuid": "{5cfa2075-477b-4ded-bdb9-8d2479544ec4}", "links": {"self": {"href": "https://api.bitbucket.org/2.0/users/%7B5cfa2075-477b-4ded-bdb9-8d2479544ec4%7D"}, "html": {"href": "https://bitbucket.org/%7B5cfa2075-477b-4ded-bdb9-8d2479544ec4%7D/"}, "avatar": {"href": "https://avatar-management--avatars.us-west-2.prod.public.atl-paas.net/557058:6ff86fcb-b7ab-44a5-b8a6-f6d9cae8b6e8/7d903d90-c5ea-4182-b7ef-0d467e9e1c74/128"}}, "nickname": "chapulina", "type": "user", "account_id": "557058:6ff86fcb-b7ab-44a5-b8a6-f6d9cae8b6e8"}, "inline": {"to": 287, "from": null, "path": "include/sdf/Actor.hh"}, "updated_on": "2019-06-20T15:16:23.690494+00:00", "type": "pullrequest_comment", "id": 106494111}, {"links": {"self": {"href": "data/repositories/osrf/sdformat/pullrequests/547/comments/106481064.json"}, "code": {"href": "https://api.bitbucket.org/2.0/repositories/osrf/sdformat/diff/mingfeisun/sdformat:f16b64336803..0b0a836f2b25?path=include%2Fsdf%2FActor.hh"}, "html": {"href": "#!/osrf/sdformat/pull-requests/547/_/diff#comment-106481064"}}, "deleted": false, "pullrequest": {"type": "pullrequest", "id": 547, "links": {"self": {"href": "data/repositories/osrf/sdformat/pullrequests/547.json"}, "html": {"href": "#!/osrf/sdformat/pull-requests/547"}}, "title": "add Actor parsing and tests"}, "content": {"raw": "It would be good to have `SetId` too", "markup": "markdown", "html": "<p>It would be good to have <code>SetId</code> too</p>", "type": "rendered"}, "created_on": "2019-06-20T14:05:30.977863+00:00", "user": {"display_name": "Louise Poubel", "uuid": "{5cfa2075-477b-4ded-bdb9-8d2479544ec4}", "links": {"self": {"href": "https://api.bitbucket.org/2.0/users/%7B5cfa2075-477b-4ded-bdb9-8d2479544ec4%7D"}, "html": {"href": "https://bitbucket.org/%7B5cfa2075-477b-4ded-bdb9-8d2479544ec4%7D/"}, "avatar": {"href": "https://avatar-management--avatars.us-west-2.prod.public.atl-paas.net/557058:6ff86fcb-b7ab-44a5-b8a6-f6d9cae8b6e8/7d903d90-c5ea-4182-b7ef-0d467e9e1c74/128"}}, "nickname": "chapulina", "type": "user", "account_id": "557058:6ff86fcb-b7ab-44a5-b8a6-f6d9cae8b6e8"}, "inline": {"to": 219, "from": null, "path": "include/sdf/Actor.hh"}, "updated_on": "2019-06-20T14:05:30.994047+00:00", "type": "pullrequest_comment", "id": 106481064}, {"links": {"self": {"href": "data/repositories/osrf/sdformat/pullrequests/547/comments/106481757.json"}, "code": {"href": "https://api.bitbucket.org/2.0/repositories/osrf/sdformat/diff/mingfeisun/sdformat:f16b64336803..0b0a836f2b25?path=include%2Fsdf%2FActor.hh"}, "html": {"href": "#!/osrf/sdformat/pull-requests/547/_/diff#comment-106481757"}}, "parent": {"id": 106481064, "links": {"self": {"href": "data/repositories/osrf/sdformat/pullrequests/547/comments/106481064.json"}, "html": {"href": "#!/osrf/sdformat/pull-requests/547/_/diff#comment-106481064"}}, "depth": 1}, "deleted": false, "pullrequest": {"type": "pullrequest", "id": 547, "links": {"self": {"href": "data/repositories/osrf/sdformat/pullrequests/547.json"}, "html": {"href": "#!/osrf/sdformat/pull-requests/547"}}, "title": "add Actor parsing and tests"}, "content": {"raw": "Yes. Do we need to check whether the `Id` has already been adopted by other trajectories? ", "markup": "markdown", "html": "<p>Yes. Do we need to check whether the <code>Id</code> has already been adopted by other trajectories? </p>", "type": "rendered"}, "created_on": "2019-06-20T14:08:33.464453+00:00", "user": {"display_name": "mingfei sun", "uuid": "{1e5a944b-56e4-4808-b81d-d6de318feadc}", "links": {"self": {"href": "https://api.bitbucket.org/2.0/users/%7B1e5a944b-56e4-4808-b81d-d6de318feadc%7D"}, "html": {"href": "https://bitbucket.org/%7B1e5a944b-56e4-4808-b81d-d6de318feadc%7D/"}, "avatar": {"href": "data/secure.gravatar.com/avatar/a4be22d43d004c04e5f8fee72a65d214d=httpsavatar-management--avatars.us-west-2.prod.public.atl-paas.netinitialsMS-1.png"}}, "nickname": "mingfeisun", "type": "user", "account_id": "557058:ad32c2b0-bebb-403e-b385-c3c1f7aa1d09"}, "inline": {"to": 219, "from": null, "path": "include/sdf/Actor.hh"}, "updated_on": "2019-06-20T14:08:33.611981+00:00", "type": "pullrequest_comment", "id": 106481757}, {"links": {"self": {"href": "data/repositories/osrf/sdformat/pullrequests/547/comments/106482130.json"}, "code": {"href": "https://api.bitbucket.org/2.0/repositories/osrf/sdformat/diff/mingfeisun/sdformat:f16b64336803..0b0a836f2b25?path=include%2Fsdf%2FActor.hh"}, "html": {"href": "#!/osrf/sdformat/pull-requests/547/_/diff#comment-106482130"}}, "parent": {"id": 106481757, "links": {"self": {"href": "data/repositories/osrf/sdformat/pullrequests/547/comments/106481757.json"}, "html": {"href": "#!/osrf/sdformat/pull-requests/547/_/diff#comment-106481757"}}, "depth": 2}, "deleted": false, "pullrequest": {"type": "pullrequest", "id": 547, "links": {"self": {"href": "data/repositories/osrf/sdformat/pullrequests/547.json"}, "html": {"href": "#!/osrf/sdformat/pull-requests/547"}}, "title": "add Actor parsing and tests"}, "content": {"raw": "I think we're not doing any uniqueness checks right now, so don't worry about it. Just the setter should be ok.", "markup": "markdown", "html": "<p>I think we're not doing any uniqueness checks right now, so don't worry about it. Just the setter should be ok.</p>", "type": "rendered"}, "created_on": "2019-06-20T14:10:40.684201+00:00", "user": {"display_name": "Louise Poubel", "uuid": "{5cfa2075-477b-4ded-bdb9-8d2479544ec4}", "links": {"self": {"href": "https://api.bitbucket.org/2.0/users/%7B5cfa2075-477b-4ded-bdb9-8d2479544ec4%7D"}, "html": {"href": "https://bitbucket.org/%7B5cfa2075-477b-4ded-bdb9-8d2479544ec4%7D/"}, "avatar": {"href": "https://avatar-management--avatars.us-west-2.prod.public.atl-paas.net/557058:6ff86fcb-b7ab-44a5-b8a6-f6d9cae8b6e8/7d903d90-c5ea-4182-b7ef-0d467e9e1c74/128"}}, "nickname": "chapulina", "type": "user", "account_id": "557058:6ff86fcb-b7ab-44a5-b8a6-f6d9cae8b6e8"}, "inline": {"to": 219, "from": null, "path": "include/sdf/Actor.hh"}, "updated_on": "2019-06-20T14:10:40.697163+00:00", "type": "pullrequest_comment", "id": 106482130}, {"links": {"self": {"href": "data/repositories/osrf/sdformat/pullrequests/547/comments/106482462.json"}, "code": {"href": "https://api.bitbucket.org/2.0/repositories/osrf/sdformat/diff/mingfeisun/sdformat:f16b64336803..0b0a836f2b25?path=include%2Fsdf%2FActor.hh"}, "html": {"href": "#!/osrf/sdformat/pull-requests/547/_/diff#comment-106482462"}}, "parent": {"id": 106482130, "links": {"self": {"href": "data/repositories/osrf/sdformat/pullrequests/547/comments/106482130.json"}, "html": {"href": "#!/osrf/sdformat/pull-requests/547/_/diff#comment-106482130"}}, "depth": 3}, "deleted": false, "pullrequest": {"type": "pullrequest", "id": 547, "links": {"self": {"href": "data/repositories/osrf/sdformat/pullrequests/547.json"}, "html": {"href": "#!/osrf/sdformat/pull-requests/547"}}, "title": "add Actor parsing and tests"}, "content": {"raw": "Sure", "markup": "markdown", "html": "<p>Sure</p>", "type": "rendered"}, "created_on": "2019-06-20T14:12:01.063917+00:00", "user": {"display_name": "mingfei sun", "uuid": "{1e5a944b-56e4-4808-b81d-d6de318feadc}", "links": {"self": {"href": "https://api.bitbucket.org/2.0/users/%7B1e5a944b-56e4-4808-b81d-d6de318feadc%7D"}, "html": {"href": "https://bitbucket.org/%7B1e5a944b-56e4-4808-b81d-d6de318feadc%7D/"}, "avatar": {"href": "data/secure.gravatar.com/avatar/a4be22d43d004c04e5f8fee72a65d214d=httpsavatar-management--avatars.us-west-2.prod.public.atl-paas.netinitialsMS-1.png"}}, "nickname": "mingfeisun", "type": "user", "account_id": "557058:ad32c2b0-bebb-403e-b385-c3c1f7aa1d09"}, "inline": {"to": 219, "from": null, "path": "include/sdf/Actor.hh"}, "updated_on": "2019-06-20T14:12:01.214600+00:00", "type": "pullrequest_comment", "id": 106482462}, {"links": {"self": {"href": "data/repositories/osrf/sdformat/pullrequests/547/comments/112131569.json"}, "html": {"href": "#!/osrf/sdformat/pull-requests/547/_/diff#comment-112131569"}}, "deleted": false, "pullrequest": {"type": "pullrequest", "id": 547, "links": {"self": {"href": "data/repositories/osrf/sdformat/pullrequests/547.json"}, "html": {"href": "#!/osrf/sdformat/pull-requests/547"}}, "title": "add Actor parsing and tests"}, "content": {"raw": "The latest changes look good to me! Could you just add tests for the new `AddXXX` functions? Thanks!", "markup": "markdown", "html": "<p>The latest changes look good to me! Could you just add tests for the new <code>AddXXX</code> functions? Thanks!</p>", "type": "rendered"}, "created_on": "2019-08-06T18:49:04.283216+00:00", "user": {"display_name": "Louise Poubel", "uuid": "{5cfa2075-477b-4ded-bdb9-8d2479544ec4}", "links": {"self": {"href": "https://api.bitbucket.org/2.0/users/%7B5cfa2075-477b-4ded-bdb9-8d2479544ec4%7D"}, "html": {"href": "https://bitbucket.org/%7B5cfa2075-477b-4ded-bdb9-8d2479544ec4%7D/"}, "avatar": {"href": "https://avatar-management--avatars.us-west-2.prod.public.atl-paas.net/557058:6ff86fcb-b7ab-44a5-b8a6-f6d9cae8b6e8/7d903d90-c5ea-4182-b7ef-0d467e9e1c74/128"}}, "nickname": "chapulina", "type": "user", "account_id": "557058:6ff86fcb-b7ab-44a5-b8a6-f6d9cae8b6e8"}, "updated_on": "2019-08-06T18:49:04.291436+00:00", "type": "pullrequest_comment", "id": 112131569}, {"links": {"self": {"href": "data/repositories/osrf/sdformat/pullrequests/547/comments/112677372.json"}, "html": {"href": "#!/osrf/sdformat/pull-requests/547/_/diff#comment-112677372"}}, "parent": {"id": 112131569, "links": {"self": {"href": "data/repositories/osrf/sdformat/pullrequests/547/comments/112131569.json"}, "html": {"href": "#!/osrf/sdformat/pull-requests/547/_/diff#comment-112131569"}}, "depth": 1}, "deleted": false, "pullrequest": {"type": "pullrequest", "id": 547, "links": {"self": {"href": "data/repositories/osrf/sdformat/pullrequests/547.json"}, "html": {"href": "#!/osrf/sdformat/pull-requests/547"}}, "title": "add Actor parsing and tests"}, "content": {"raw": "I have some suggestions on this PR: https://bitbucket.org/mingfeisun/sdformat/pull-requests/1/\n\nReady to approve once the tests are in.", "markup": "markdown", "html": "<p>I have some suggestions on this PR: <a href=\"https://bitbucket.org/mingfeisun/sdformat/pull-requests/1/\" rel=\"nofollow\" class=\"ap-connect-link\">https://bitbucket.org/mingfeisun/sdformat/pull-requests/1/</a></p>\n<p>Ready to approve once the tests are in.</p>", "type": "rendered"}, "created_on": "2019-08-11T22:28:46.955244+00:00", "user": {"display_name": "Louise Poubel", "uuid": "{5cfa2075-477b-4ded-bdb9-8d2479544ec4}", "links": {"self": {"href": "https://api.bitbucket.org/2.0/users/%7B5cfa2075-477b-4ded-bdb9-8d2479544ec4%7D"}, "html": {"href": "https://bitbucket.org/%7B5cfa2075-477b-4ded-bdb9-8d2479544ec4%7D/"}, "avatar": {"href": "https://avatar-management--avatars.us-west-2.prod.public.atl-paas.net/557058:6ff86fcb-b7ab-44a5-b8a6-f6d9cae8b6e8/7d903d90-c5ea-4182-b7ef-0d467e9e1c74/128"}}, "nickname": "chapulina", "type": "user", "account_id": "557058:6ff86fcb-b7ab-44a5-b8a6-f6d9cae8b6e8"}, "updated_on": "2019-08-11T22:28:46.965513+00:00", "type": "pullrequest_comment", "id": 112677372}, {"links": {"self": {"href": "data/repositories/osrf/sdformat/pullrequests/547/comments/113187874.json"}, "code": {"href": "https://api.bitbucket.org/2.0/repositories/osrf/sdformat/diff/mingfeisun/sdformat:4550129c9650..3de3005c5141?path=include%2Fsdf%2FActor.hh"}, "html": {"href": "#!/osrf/sdformat/pull-requests/547/_/diff#comment-113187874"}}, "deleted": false, "pullrequest": {"type": "pullrequest", "id": 547, "links": {"self": {"href": "data/repositories/osrf/sdformat/pullrequests/547.json"}, "html": {"href": "#!/osrf/sdformat/pull-requests/547"}}, "title": "add Actor parsing and tests"}, "content": {"raw": "make the argument const ref?", "markup": "markdown", "html": "<p>make the argument const ref?</p>", "type": "rendered"}, "created_on": "2019-08-15T01:13:59.127358+00:00", "user": {"display_name": "Ian Chen", "uuid": "{eaa6fca5-6deb-43f6-907f-971c144735dd}", "links": {"self": {"href": "https://api.bitbucket.org/2.0/users/%7Beaa6fca5-6deb-43f6-907f-971c144735dd%7D"}, "html": {"href": "https://bitbucket.org/%7Beaa6fca5-6deb-43f6-907f-971c144735dd%7D/"}, "avatar": {"href": "https://avatar-management--avatars.us-west-2.prod.public.atl-paas.net/557058:10b01d41-a2e9-4a41-a907-e6e2f03b6cd5/1e4adcdf-1946-4280-9aea-eb5f15a7f912/128"}}, "nickname": "Ian Chen", "type": "user", "account_id": "557058:10b01d41-a2e9-4a41-a907-e6e2f03b6cd5"}, "inline": {"to": 174, "from": null, "path": "include/sdf/Actor.hh"}, "updated_on": "2019-08-15T01:13:59.133742+00:00", "type": "pullrequest_comment", "id": 113187874}, {"links": {"self": {"href": "data/repositories/osrf/sdformat/pullrequests/547/comments/113187928.json"}, "code": {"href": "https://api.bitbucket.org/2.0/repositories/osrf/sdformat/diff/mingfeisun/sdformat:4550129c9650..3de3005c5141?path=include%2Fsdf%2FActor.hh"}, "html": {"href": "#!/osrf/sdformat/pull-requests/547/_/diff#comment-113187928"}}, "deleted": false, "pullrequest": {"type": "pullrequest", "id": 547, "links": {"self": {"href": "data/repositories/osrf/sdformat/pullrequests/547.json"}, "html": {"href": "#!/osrf/sdformat/pull-requests/547"}}, "title": "add Actor parsing and tests"}, "content": {"raw": "some of the primitive type args in this PR are `const` but some are not.  It would be nice to be consistent", "markup": "markdown", "html": "<p>some of the primitive type args in this PR are <code>const</code> but some are not.  It would be nice to be consistent</p>", "type": "rendered"}, "created_on": "2019-08-15T01:15:20.314827+00:00", "user": {"display_name": "Ian Chen", "uuid": "{eaa6fca5-6deb-43f6-907f-971c144735dd}", "links": {"self": {"href": "https://api.bitbucket.org/2.0/users/%7Beaa6fca5-6deb-43f6-907f-971c144735dd%7D"}, "html": {"href": "https://bitbucket.org/%7Beaa6fca5-6deb-43f6-907f-971c144735dd%7D/"}, "avatar": {"href": "https://avatar-management--avatars.us-west-2.prod.public.atl-paas.net/557058:10b01d41-a2e9-4a41-a907-e6e2f03b6cd5/1e4adcdf-1946-4280-9aea-eb5f15a7f912/128"}}, "nickname": "Ian Chen", "type": "user", "account_id": "557058:10b01d41-a2e9-4a41-a907-e6e2f03b6cd5"}, "inline": {"to": 166, "from": null, "path": "include/sdf/Actor.hh"}, "updated_on": "2019-08-15T01:15:20.322415+00:00", "type": "pullrequest_comment", "id": 113187928}, {"links": {"self": {"href": "data/repositories/osrf/sdformat/pullrequests/547/comments/113310909.json"}, "html": {"href": "#!/osrf/sdformat/pull-requests/547/_/diff#comment-113310909"}}, "deleted": false, "pullrequest": {"type": "pullrequest", "id": 547, "links": {"self": {"href": "data/repositories/osrf/sdformat/pullrequests/547.json"}, "html": {"href": "#!/osrf/sdformat/pull-requests/547"}}, "title": "add Actor parsing and tests"}, "content": {"raw": "apart from a couple of minor comments, this looks good to me.", "markup": "markdown", "html": "<p>apart from a couple of minor comments, this looks good to me.</p>", "type": "rendered"}, "created_on": "2019-08-15T21:16:25.528247+00:00", "user": {"display_name": "Ian Chen", "uuid": "{eaa6fca5-6deb-43f6-907f-971c144735dd}", "links": {"self": {"href": "https://api.bitbucket.org/2.0/users/%7Beaa6fca5-6deb-43f6-907f-971c144735dd%7D"}, "html": {"href": "https://bitbucket.org/%7Beaa6fca5-6deb-43f6-907f-971c144735dd%7D/"}, "avatar": {"href": "https://avatar-management--avatars.us-west-2.prod.public.atl-paas.net/557058:10b01d41-a2e9-4a41-a907-e6e2f03b6cd5/1e4adcdf-1946-4280-9aea-eb5f15a7f912/128"}}, "nickname": "Ian Chen", "type": "user", "account_id": "557058:10b01d41-a2e9-4a41-a907-e6e2f03b6cd5"}, "updated_on": "2019-08-15T21:16:25.537729+00:00", "type": "pullrequest_comment", "id": 113310909}, {"links": {"self": {"href": "data/repositories/osrf/sdformat/pullrequests/547/comments/113314403.json"}, "html": {"href": "#!/osrf/sdformat/pull-requests/547/_/diff#comment-113314403"}}, "parent": {"id": 113310909, "links": {"self": {"href": "data/repositories/osrf/sdformat/pullrequests/547/comments/113310909.json"}, "html": {"href": "#!/osrf/sdformat/pull-requests/547/_/diff#comment-113310909"}}, "depth": 1}, "deleted": false, "pullrequest": {"type": "pullrequest", "id": 547, "links": {"self": {"href": "data/repositories/osrf/sdformat/pullrequests/547.json"}, "html": {"href": "#!/osrf/sdformat/pull-requests/547"}}, "title": "add Actor parsing and tests"}, "content": {"raw": "@{557058:ad32c2b0-bebb-403e-b385-c3c1f7aa1d09} will address your comments before we merge :wink: ", "markup": "markdown", "html": "<p><span class=\"ap-mention\" data-atlassian-id=\"557058:ad32c2b0-bebb-403e-b385-c3c1f7aa1d09\">@mingfei sun</span> will address your comments before we merge <img class=\"emoji\" src=\"data/pf-emoji-service--cdn.us-east-1.prod.public.atl-paas.net/standard/551c9814-1d37-4573-819d-afab3afeaf32/48x48/1f609.png\" alt=\"\ud83d\ude09\" title=\":wink:\" data-emoji-short-name=\":wink:\" /> </p>", "type": "rendered"}, "created_on": "2019-08-15T22:00:55.850844+00:00", "user": {"display_name": "Louise Poubel", "uuid": "{5cfa2075-477b-4ded-bdb9-8d2479544ec4}", "links": {"self": {"href": "https://api.bitbucket.org/2.0/users/%7B5cfa2075-477b-4ded-bdb9-8d2479544ec4%7D"}, "html": {"href": "https://bitbucket.org/%7B5cfa2075-477b-4ded-bdb9-8d2479544ec4%7D/"}, "avatar": {"href": "https://avatar-management--avatars.us-west-2.prod.public.atl-paas.net/557058:6ff86fcb-b7ab-44a5-b8a6-f6d9cae8b6e8/7d903d90-c5ea-4182-b7ef-0d467e9e1c74/128"}}, "nickname": "chapulina", "type": "user", "account_id": "557058:6ff86fcb-b7ab-44a5-b8a6-f6d9cae8b6e8"}, "updated_on": "2019-08-15T22:00:55.866775+00:00", "type": "pullrequest_comment", "id": 113314403}, {"links": {"self": {"href": "data/repositories/osrf/sdformat/pullrequests/547/comments/113430252.json"}, "html": {"href": "#!/osrf/sdformat/pull-requests/547/_/diff#comment-113430252"}}, "parent": {"id": 113314403, "links": {"self": {"href": "data/repositories/osrf/sdformat/pullrequests/547/comments/113314403.json"}, "html": {"href": "#!/osrf/sdformat/pull-requests/547/_/diff#comment-113314403"}}, "depth": 2}, "deleted": false, "pullrequest": {"type": "pullrequest", "id": 547, "links": {"self": {"href": "data/repositories/osrf/sdformat/pullrequests/547.json"}, "html": {"href": "#!/osrf/sdformat/pull-requests/547"}}, "title": "add Actor parsing and tests"}, "content": {"raw": "Thanks for addressing the comments, @{557058:ad32c2b0-bebb-403e-b385-c3c1f7aa1d09} ! We just need to pass pose by reference on `SetPose` and we're good to go!", "markup": "markdown", "html": "<p>Thanks for addressing the comments, <span class=\"ap-mention\" data-atlassian-id=\"557058:ad32c2b0-bebb-403e-b385-c3c1f7aa1d09\">@mingfei sun</span> ! We just need to pass pose by reference on <code>SetPose</code> and we're good to go!</p>", "type": "rendered"}, "created_on": "2019-08-16T18:01:52.643297+00:00", "user": {"display_name": "Louise Poubel", "uuid": "{5cfa2075-477b-4ded-bdb9-8d2479544ec4}", "links": {"self": {"href": "https://api.bitbucket.org/2.0/users/%7B5cfa2075-477b-4ded-bdb9-8d2479544ec4%7D"}, "html": {"href": "https://bitbucket.org/%7B5cfa2075-477b-4ded-bdb9-8d2479544ec4%7D/"}, "avatar": {"href": "https://avatar-management--avatars.us-west-2.prod.public.atl-paas.net/557058:6ff86fcb-b7ab-44a5-b8a6-f6d9cae8b6e8/7d903d90-c5ea-4182-b7ef-0d467e9e1c74/128"}}, "nickname": "chapulina", "type": "user", "account_id": "557058:6ff86fcb-b7ab-44a5-b8a6-f6d9cae8b6e8"}, "updated_on": "2019-08-16T18:01:52.664662+00:00", "type": "pullrequest_comment", "id": 113430252}, {"links": {"self": {"href": "data/repositories/osrf/sdformat/pullrequests/547/comments/113315409.json"}, "code": {"href": "https://api.bitbucket.org/2.0/repositories/osrf/sdformat/diff/mingfeisun/sdformat:4550129c9650..3de3005c5141?path=include%2Fsdf%2FActor.hh"}, "html": {"href": "#!/osrf/sdformat/pull-requests/547/_/diff#comment-113315409"}}, "deleted": false, "pullrequest": {"type": "pullrequest", "id": 547, "links": {"self": {"href": "data/repositories/osrf/sdformat/pullrequests/547.json"}, "html": {"href": "#!/osrf/sdformat/pull-requests/547"}}, "title": "add Actor parsing and tests"}, "content": {"raw": "This field is [deprecated](#!/osrf/sdformat/src/08ea83caa185e305fcc5d21b80e0b388cf9901b0/sdf/1.6/actor.sdf#lines-10) on the spec, so we can remove it. Thanks for pointing it out [here](https://bitbucket.org/ignitionrobotics/ign-msgs/pull-requests/147/add-actor-proto/diff#comment-113260575)!", "markup": "markdown", "html": "<p>This field is <a data-is-external-link=\"true\" href=\"#!/osrf/sdformat/src/08ea83caa185e305fcc5d21b80e0b388cf9901b0/sdf/1.6/actor.sdf#lines-10\" rel=\"nofollow\">deprecated</a> on the spec, so we can remove it. Thanks for pointing it out <a data-is-external-link=\"true\" href=\"https://bitbucket.org/ignitionrobotics/ign-msgs/pull-requests/147/add-actor-proto/diff#comment-113260575\" rel=\"nofollow\">here</a>!</p>", "type": "rendered"}, "created_on": "2019-08-15T22:15:02.339910+00:00", "user": {"display_name": "Louise Poubel", "uuid": "{5cfa2075-477b-4ded-bdb9-8d2479544ec4}", "links": {"self": {"href": "https://api.bitbucket.org/2.0/users/%7B5cfa2075-477b-4ded-bdb9-8d2479544ec4%7D"}, "html": {"href": "https://bitbucket.org/%7B5cfa2075-477b-4ded-bdb9-8d2479544ec4%7D/"}, "avatar": {"href": "https://avatar-management--avatars.us-west-2.prod.public.atl-paas.net/557058:6ff86fcb-b7ab-44a5-b8a6-f6d9cae8b6e8/7d903d90-c5ea-4182-b7ef-0d467e9e1c74/128"}}, "nickname": "chapulina", "type": "user", "account_id": "557058:6ff86fcb-b7ab-44a5-b8a6-f6d9cae8b6e8"}, "inline": {"to": 321, "from": null, "path": "include/sdf/Actor.hh"}, "updated_on": "2019-08-15T22:15:02.346769+00:00", "type": "pullrequest_comment", "id": 113315409}, {"links": {"self": {"href": "data/repositories/osrf/sdformat/pullrequests/547/comments/113435101.json"}, "code": {"href": "https://api.bitbucket.org/2.0/repositories/osrf/sdformat/diff/mingfeisun/sdformat:2528eead2194..3de3005c5141?path=src%2FActor.cc"}, "html": {"href": "#!/osrf/sdformat/pull-requests/547/_/diff#comment-113435101"}}, "deleted": false, "pullrequest": {"type": "pullrequest", "id": 547, "links": {"self": {"href": "data/repositories/osrf/sdformat/pullrequests/547.json"}, "html": {"href": "#!/osrf/sdformat/pull-requests/547"}}, "title": "add Actor parsing and tests"}, "content": {"raw": "missing `const` for Pose3d type", "markup": "markdown", "html": "<p>missing <code>const</code> for Pose3d type</p>", "type": "rendered"}, "created_on": "2019-08-16T18:52:39.189406+00:00", "user": {"display_name": "Steve Peters", "uuid": "{2ccfed09-18b8-4921-8d58-15ef01092802}", "links": {"self": {"href": "https://api.bitbucket.org/2.0/users/%7B2ccfed09-18b8-4921-8d58-15ef01092802%7D"}, "html": {"href": "https://bitbucket.org/%7B2ccfed09-18b8-4921-8d58-15ef01092802%7D/"}, "avatar": {"href": "data/secure.gravatar.com/avatar/1fb4816dad9e68337d3096f750951f6cd=httpsavatar-management--avatars.us-west-2.prod.public.atl-paas.netinitialsSP-1.png"}}, "nickname": "Steven Peters", "type": "user", "account_id": "557058:5de38267-b118-494c-aa76-4fab35448816"}, "inline": {"to": 334, "from": null, "path": "src/Actor.cc"}, "updated_on": "2019-08-16T18:52:39.199968+00:00", "type": "pullrequest_comment", "id": 113435101}], "page": 1, "size": 34}