{"links": {"self": {"href": "data/repositories/osrf/sdformat/pullrequests/235/comments/11718234.json"}, "code": {"href": "https://api.bitbucket.org/2.0/repositories/osrf/sdformat/diff/osrf/sdformat:50855c24792e..4bc95f7135a7?path=src%2Fparser_urdf.cc"}, "html": {"href": "#!/osrf/sdformat/pull-requests/235/_/diff#comment-11718234"}}, "deleted": false, "pullrequest": {"type": "pullrequest", "id": 235, "links": {"self": {"href": "data/repositories/osrf/sdformat/pullrequests/235.json"}, "html": {"href": "#!/osrf/sdformat/pull-requests/235"}}, "title": "collision_blobs for sdf3 branch"}, "content": {"raw": "There's a lot of repeated code between this block and the next. What if they were combined like in 2a4f2ecc1da1 (branch `collision_blobs_sdf3_deduplicate`)?", "markup": "markdown", "html": "<p>There's a lot of repeated code between this block and the next. What if they were combined like in <a href=\"#!/osrf/sdformat/commits/2a4f2ecc1da1\" rel=\"nofollow\" class=\"ap-connect-link\">2a4f2ecc1da1</a> (branch <code>collision_blobs_sdf3_deduplicate</code>)?</p>", "type": "rendered"}, "created_on": "2015-11-12T01:14:00.135684+00:00", "user": {"display_name": "Steve Peters", "uuid": "{2ccfed09-18b8-4921-8d58-15ef01092802}", "links": {"self": {"href": "https://api.bitbucket.org/2.0/users/%7B2ccfed09-18b8-4921-8d58-15ef01092802%7D"}, "html": {"href": "https://bitbucket.org/%7B2ccfed09-18b8-4921-8d58-15ef01092802%7D/"}, "avatar": {"href": "data/secure.gravatar.com/avatar/1fb4816dad9e68337d3096f750951f6cd=httpsavatar-management--avatars.us-west-2.prod.public.atl-paas.netinitialsSP-1.png"}}, "nickname": "Steven Peters", "type": "user", "account_id": "557058:5de38267-b118-494c-aa76-4fab35448816"}, "inline": {"to": 1394, "from": null, "outdated": true, "path": "src/parser_urdf.cc"}, "updated_on": "2015-11-12T01:14:00.137673+00:00", "type": "pullrequest_comment", "id": 11718234}